Workbook

Sheet PRINCIPAL
A1: Subclasse CNAE 2.0 | B1: Denominação | C1: IN 003 visa Alto Risco | D1: IN visa 003 Médio Risco | E1: IN visa 003 Baixo Risco | F1: IMA BAIXO RISCO
A2: 0111-3/01 | B2: Cultivo de arroz | C2: =IF(COUNTIF('IN 003 VISA'!G:G,A2)>0,"SIM","NÃO") -> NÃO | D2: =IF(COUNTIF('IN 003 VISA'!D:D,A2)>0,"SIM","NÃO") -> NÃO | E2: =IF(COUNTIF('IN 003 VISA'!A:A,A2)>0,"SIM","NÃO") -> SIM | F2: =IF(COUNTIF('Lista IMA'!A:A,A2)>0,"SIM","NÃO") -> NÃO
A3: 0111-3/02 | B3: Cultivo de milho | C3: =IF(COUNTIF('IN 003 VISA'!G:G,A3)>0,"SIM","NÃO") -> NÃO | D3: =IF(COUNTIF('IN 003 VISA'!D:D,A3)>0,"SIM","NÃO") -> NÃO | E3: =IF(COUNTIF('IN 003 VISA'!A:A,A3)>0,"SIM","NÃO") -> SIM | F3: =IF(COUNTIF('Lista IMA'!A:A,A3)>0,"SIM","NÃO") -> SIM
A4: 0111-3/03 | B4: Cultivo de trigo | C4: =IF(COUNTIF('IN 003 VISA'!G:G,A4)>0,"SIM","NÃO") -> NÃO | D4: =IF(COUNTIF('IN 003 VISA'!D:D,A4)>0,"SIM","NÃO") -> NÃO | E4: =IF(COUNTIF('IN 003 VISA'!A:A,A4)>0,"SIM","NÃO") -> SIM | F4: =IF(COUNTIF('Lista IMA'!A:A,A4)>0,"SIM","NÃO") -> SIM
A5: 0111-3/99 | B5: Cultivo de outros cereais não especificados anteriormente | C5: =IF(COUNTIF('IN 003 VISA'!G:G,A5)>0,"SIM","NÃO") -> NÃO | D5: =IF(COUNTIF('IN 003 VISA'!D:D,A5)>0,"SIM","NÃO") -> NÃO | E5: =IF(COUNTIF('IN 003 VISA'!A:A,A5)>0,"SIM","NÃO") -> SIM | F5: =IF(COUNTIF('Lista IMA'!A:A,A5)>0,"SIM","NÃO") -> SIM
A6: 0112-1/01 | B6: Cultivo de algodão herbáceo | C6: =IF(COUNTIF('IN 003 VISA'!G:G,A6)>0,"SIM","NÃO") -> NÃO | D6: =IF(COUNTIF('IN 003 VISA'!D:D,A6)>0,"SIM","NÃO") -> NÃO | E6: =IF(COUNTIF('IN 003 VISA'!A:A,A6)>0,"SIM","NÃO") -> SIM | F6: =IF(COUNTIF('Lista IMA'!A:A,A6)>0,"SIM","NÃO") -> SIM
A7: 0112-1/02 | B7: Cultivo de juta | C7: =IF(COUNTIF('IN 003 VISA'!G:G,A7)>0,"SIM","NÃO") -> NÃO | D7: =IF(COUNTIF('IN 003 VISA'!D:D,A7)>0,"SIM","NÃO") -> NÃO | E7: =IF(COUNTIF('IN 003 VISA'!A:A,A7)>0,"SIM","NÃO") -> SIM | F7: =IF(COUNTIF('Lista IMA'!A:A,A7)>0,"SIM","NÃO") -> SIM
A8: 0112-1/99 | B8: Cultivo de outras fibras de lavoura temporária não especificadas anteriormente | C8: =IF(COUNTIF('IN 003 VISA'!G:G,A8)>0,"SIM","NÃO") -> NÃO | D8: =IF(COUNTIF('IN 003 VISA'!D:D,A8)>0,"SIM","NÃO") -> NÃO | E8: =IF(COUNTIF('IN 003 VISA'!A:A,A8)>0,"SIM","NÃO") -> SIM | F8: =IF(COUNTIF('Lista IMA'!A:A,A8)>0,"SIM","NÃO") -> SIM
A9: 0113-0/00 | B9: Cultivo de cana-de-açúcar | C9: =IF(COUNTIF('IN 003 VISA'!G:G,A9)>0,"SIM","NÃO") -> NÃO | D9: =IF(COUNTIF('IN 003 VISA'!D:D,A9)>0,"SIM","NÃO") -> NÃO | E9: =IF(COUNTIF('IN 003 VISA'!A:A,A9)>0,"SIM","NÃO") -> SIM | F9: =IF(COUNTIF('Lista IMA'!A:A,A9)>0,"SIM","NÃO") -> SIM
A10: 0114-8/00 | B10: Cultivo de fumo | C10: =IF(COUNTIF('IN 003 VISA'!G:G,A10)>0,"SIM","NÃO") -> NÃO | D10: =IF(COUNTIF('IN 003 VISA'!D:D,A10)>0,"SIM","NÃO") -> NÃO | E10: =IF(COUNTIF('IN 003 VISA'!A:A,A10)>0,"SIM","NÃO") -> SIM | F10: =IF(COUNTIF('Lista IMA'!A:A,A10)>0,"SIM","NÃO") -> SIM
A11: 0115-6/00 | B11: Cultivo de soja | C11: =IF(COUNTIF('IN 003 VISA'!G:G,A11)>0,"SIM","NÃO") -> NÃO | D11: =IF(COUNTIF('IN 003 VISA'!D:D,A11)>0,"SIM","NÃO") -> NÃO | E11: =IF(COUNTIF('IN 003 VISA'!A:A,A11)>0,"SIM","NÃO") -> SIM | F11: =IF(COUNTIF('Lista IMA'!A:A,A11)>0,"SIM","NÃO") -> SIM
A12: 0116-4/01 | B12: Cultivo de amendoim | C12: =IF(COUNTIF('IN 003 VISA'!G:G,A12)>0,"SIM","NÃO") -> NÃO | D12: =IF(COUNTIF('IN 003 VISA'!D:D,A12)>0,"SIM","NÃO") -> NÃO | E12: =IF(COUNTIF('IN 003 VISA'!A:A,A12)>0,"SIM","NÃO") -> SIM | F12: =IF(COUNTIF('Lista IMA'!A:A,A12)>0,"SIM","NÃO") -> SIM
A13: 0116-4/02 | B13: Cultivo de girassol | C13: =IF(COUNTIF('IN 003 VISA'!G:G,A13)>0,"SIM","NÃO") -> NÃO | D13: =IF(COUNTIF('IN 003 VISA'!D:D,A13)>0,"SIM","NÃO") -> NÃO | E13: =IF(COUNTIF('IN 003 VISA'!A:A,A13)>0,"SIM","NÃO") -> SIM | F13: =IF(COUNTIF('Lista IMA'!A:A,A13)>0,"SIM","NÃO") -> SIM
... A1338: 9900-8/00 | B1338: Organismos internacionais e outras instituições extraterritoriais | C1338: =IF(COUNTIF('IN 003 VISA'!G:G,A1338)>0,"SIM","NÃO") -> NÃO | D1338: =IF(COUNTIF('IN 003 VISA'!D:D,A1338)>0,"SIM","NÃO") -> NÃO | E1338: =IF(COUNTIF('IN 003 VISA'!A:A,A1338)>0,"SIM","NÃO") -> SIM | F1338: =IF(COUNTIF('Lista IMA'!A:A,A1338)>0,"SIM","NÃO") -> SIM

Sheet Lei Estadual 18091-21
A1: Nº | B1: Atividade Econômica
A2: 1 | B2: Agenciamento de espaços para publicidade, exceto em veículos de comunicação (Código CNAE:7312200) | C2: 7312-2/00
A3: 2 | B3: Agenciamento de profissionais para atividades esportivas, culturais e artísticas (Código CNAE:7490105) | C3: 7490-1/05
A4: 3 | B4: Agências de notícias (Código CNAE:6391700) | C4: 6391-7/00
A5: 4 | B5: Agências de publicidade (Código CNAE:7311400) | C5: 7311-4/00
A6: 5 | B6: Agências de viagens (Código CNAE:7911200) | C6: 7911-2/00
A7: 6 | B7: Agências matrimoniais (Código CNAE:9609202) | C7: 9609-2/02
A8: 7 | B8: Albergues, exceto assistenciais (Código CNAE:5590601) | C8: 5590-6/01
A9: 8 | B9: Aluguel de aparelhos de jogos eletrônicos (Código CNAE:7729201) | C9: 7729-2/01
A10: 9 | B10: Aluguel de equipamentos recreativos e esportivos (Código CNAE:7721700) | C10: 7721-7/00
A11: 10 | B11: Aluguel de fitas de vídeo, DVDs e similares (Código CNAE:7722500) | C11: 7722-5/00
A12: 11 | B12: Aluguel de imóveis próprios (Código CNAE:6810202) | C12: 6810-2/02
A13: 12 | B13: Aluguel de máquinas e equipamentos para escritório (Código CNAE:7733100) | C13: 7733-1/00
... A291: 290 | B291: Web design (Código CNAE:6201502) | C291: 6201-5/02

Sheet Res 51 e 59
A1: Código CNAE | B1: Descrição da atividade econômica | C1: Condição para classificação em baixo risco, "baixo risco A", risco leve, irrelevante ou inexistente
A2: 0121-1/01 | B2: Horticultura, exceto morango
A3: 1031-7/00 | B3: Fabricação de conservas de frutas | C3: Desde que o resultado do exercício da atividade econômica não seja diferente de produto artesanal
A4: 1032-5/99 | B4: Fabricação de conservas de legumes e outros vegetais, exceto palmito | C4: Desde que o resultado do exercício da atividade econômica não seja diferente de produto artesanal
A5: 1033-3/02 | B5: Fabricação de sucos de frutas, hortaliças e legumes, exceto concentrados
A6: 1091-1/02 | B6: Fabricação de produtos de padaria e confeitaria com predominância de produção própria
A7: 1092-9/00 | B7: Fabricação de biscoitos e bolachas | C7: Desde que o resultado do exercício da atividade econômica não seja diferente de produto artesanal
A8: 1093-7/01 | B8: Fabricação de produtos derivados do cacau e de chocolates | C8: Desde que o resultado do exercício da atividade econômica não seja diferente de produto artesanal
A9: 1093-7/02 | B9: Fabricação de frutas cristalizadas, balas e semelhantes | C9: Desde que o resultado do exercício da atividade econômica não seja diferente de produto artesanal
A10: 1094-5/00 | B10: Fabricação de massas alimentícias | C10: Desde que o resultado do exercício da atividade econômica não seja diferente de produto artesanal
A11: 1095-3/00 | B11: Fabricação de especiarias, molhos, temperos e condimentos | C11: Desde que o resultado do exercício da atividade econômica não seja diferente de especiaria ou condimento desidratado produzido artesanalmente
A12: 1096-1/00 | B12: Fabricação de alimentos e pratos prontos | C12: Desde que o resultado do exercício da atividade econômica não seja diferente de produto artesanal
A13: 1099-6/04 | B13: Fabricação de gelo comum | C13: Desde que o gelo fabricado não seja para consumo humano e não entrará em contato com alimentos e bebidas
A14: 1311-1/00 | B14: Preparação e fiação de fibras de algodão
A15: 1312-0/00 | B15: Preparação e fiação de fibras têxteis naturais, exceto algodão
A16: 1340-5/99 | B16: Outros serviços de acabamento em fios, tecidos, artefatos têxteis e peças do vestuário
A17: 1351-1/00 | B17: Fabricação de artefatos têxteis para uso doméstico
A18: 1354-5/00 | B18: Fabricação de tecidos especiais, inclusive artefatos
A19: 1359-6/00 | B19: Fabricação de outros produtos têxteis não especificados anteriormente
A20: 1411-8/01 | B20: Confecção de roupas íntimas
A21: 1411-8/02 | B21: Facção de roupas íntimas
A22: 1412-6/01 | B22: Confecção de peças do vestuário, exceto roupas íntimas e as confeccionadas sob medida
A23: 1412-6/02 | B23: Confecção, sob medida, de peças do vestuário, exceto roupas íntimas
A24: 1412-6/03 | B24: Facção de peças do vestuário, exceto roupas íntimas
A25: 1413-4/01 | B25: Confecção de roupas profissionais, exceto sob medida
... A35: 1822-9/99 | B35: Serviços de acabamentos gráficos, exceto encadernação e plastificação
A36: 2319-2/00 | B36: Fabricação de artigos de vidro | C36: Desde que o resultado do exercício da atividade econômica não seja um produto industrial, não haja operações de espelhação e não haja produção de peças de fibra de vidro
A37: 2399-1/01 | B37: Decoração, lapidação, gravação, vitrificação e outros trabalhos em cerâmica, louça, vidro e cristal
A38: 2539-0/01 | B38: Serviços de usinagem, tornearia e solda | C38: Desde que não haja operações de jateamento (jato de areia)
A39: 3250-7/06 | B39: Serviços de prótese dentária
A40: 3250-7/07 | B40: Fabricação de artigos ópticos | C40: Desde que não haja fabricação de produto para saúde
A41: 3291-4/00 | B41: Fabricação de escovas, pincéis e vassouras | C41: Desde que não haja no exercício a fabricação de escova dental
A42: 3299-0/02 | B42: Fabricação de canetas, lápis e outros artigos para escritório | C42: Desde que não haja armazenamento e/ou geração de resíduos químicos perigosos
A43: 3299-0/06 | B43: Fabricação de velas, inclusive decorativas | C43: Desde que não haja no exercício da atividade a fabricação de velas, sebo e/ou estearina utilizadas como cosmético ou saneante
A44: 3312-1/02 | B44: Manutenção e reparação de aparelhos e instrumentos de medida, teste e controle
A45: 3312-1/04 | B45: Manutenção e reparação de equipamentos e instrumentos ópticos
A46: 3313-9/02 | B46: Manutenção e reparação de baterias e acumuladores elétricos, exceto para veículos
A47: 3314-7/01 | B47: Manutenção e reparação de máquinas motrizes Não- elétricas
A48: 3314-7/02 | B48: Manutenção e reparação de equipamentos hidráulicos e pneumáticos, exceto válvulas
A49: 3314-7/03 | B49: Manutenção e reparação de válvulas industriais
A50: 3314-7/06 | B50: Manutenção e reparação de máquinas, aparelhos e equipamentos para instalações térmicas
A51: 3314-7/07 | B51: Manutenção e reparação de máquinas e aparelhos de refrigeração e ventilação para uso industrial e comercial
A52: 3314-7/09 | B52: Manutenção e reparação de máquinas de escrever, calcular e de outros equipamentos Não-eletrônicos para escritório
A53: 3314-7/12 | B53: Manutenção e reparação de tratores agrícolas
A54: 3314-7/13 | B54: Manutenção e reparação de máquinas-ferramenta
A55: 3329-5/01 | B55: Serviços de montagem de móveis de qualquer material
... A118: 4713-0/02 | B118: Lojas de variedades, exceto lojas de departamentos ou magazines
A119: 1030352 | B119: Padaria e confeitaria com predominância de revenda
A120: 4721-1/04 | B120: Comércio varejista de doces, balas, bombons e semelhantes
A121: 4722-9/01 | B121: Comércio varejista de carnes - açougues
A122: 4723-7/00 | B122: Comércio varejista de bebidas
A123: 4729-6/02 | B123: Comércio varejista de mercadorias em lojas de conveniência
A124: 4729-6/99 | B124: Comércio varejista de produtos alimentícios em geral ou especializado em produtos alimentícios não especificados anteriormente
A125: 4741-5/00 | B125: Comércio varejista de tintas e materiais para pintura
A126: 4742-3/00 | B126: Comércio varejista de material elétrico
A127: 4743-1/00 | B127: Comércio varejista de vidros
A128: 4744-0/01 | B128: Comércio varejista de ferragens e ferramentas
A129: 4744-0/03 | B129: Comércio varejista de materiais hidráulicos
A130: 4744-0/06 | B130: Comércio varejista de pedras para revestimento
A131: 4744-0/99 | B131: Comércio varejista de materiais de construção em geral
... A193: 6202-3/00 | B193: Desenvolvimento e licenciamento de programas de computador customizáveis
A194: 6203-1/00 | B194: Desenvolvimento e licenciamento de programas de computador Não-customizáveis | C194: Desde que não haja o desenvolvimento de softwares que realizam ou influenciam diretamente no diagnóstico, monitoramento, terapia (tratamento) para a saúde
A195: 6204-0/00 | B195: Consultoria em tecnologia da informação
A196: 6209-1/00 | B196: Suporte técnico, manutenção e outros serviços em tecnologia da informação
A197: 6311-9/00 | B197: Tratamento de dados, provedores de serviços de aplicação e serviços de hospedagem na internet
A198: 6319-4/00 | B198: Portais, provedores de conteúdo e outros serviços de informação na internet
A199: 6391-7/00 | B199: Agências de notícias
A200: 6511-1/02 | B200: Planos de auxílio-funeral
A201: 6621-5/01 | B201: Peritos e avaliadores de seguros
A202: 6621-5/02 | B202: Auditoria e consultoria atuarial
A203: 6810-2/01 | B203: Compra e venda de imóveis próprios
A204: 6810-2/02 | B204: Aluguel de imóveis próprios
A205: 6821-8/01 | B205: Corretagem na compra e venda e avaliação de imóveis
A206: 6821-8/02 | B206: Corretagem no aluguel de imóveis
... A218: 7119-7/99 | B218: Atividades técnicas relacionadas à engenharia e arquitetura não especificadas anteriormente
A219: 7120-1/00 | B219: Testes e análises técnicas | C219: Desde que não haja no exercício da atividade a análise de produto sujeito à vigilância sanitária
A220: 7210-0/00 | B220: Pesquisa e desenvolvimento experimental em ciências físicas e naturais
A221: 7220-7/00 | B221: Pesquisa e desenvolvimento experimental em ciências sociais e humanas
A222: 7311-4/00 | B222: Agências de publicidade
A223: 7312-2/00 | B223: Agenciamento de espaços para publicidade, exceto em veículos de comunicação
A224: 7319-0/02 | B224: Promoção de vendas
A225: 7319-0/03 | B225: Marketing direto
A226: 7319-0/04 | B226: Consultoria em publicidade
A227: 7320-3/00 | B227: Pesquisas de mercado e de opinião pública
A228: 7410-2/02 | B228: Design de interiores
A229: 7410-2/03 | B229: Design de produto
A230: 7410-2/99 | B230: Atividades de design não especificadas anteriormente
A231: 7420-0/01 | B231: Atividades de produção de fotografias, exceto aérea e submarina
... A239: 7490-1/99 | B239: Outras atividades profissionais, científicas e técnicas não especificadas anteriormente
A240: 7500-1/00 | B240: Atividades veterinárias | C240: Desde que o resultado do exercício da atividade não inclua a comercialização e/ou uso de medicamentos controlados e/ou equipamentos de diagnóstico por imagem
A241: 7721-7/00 | B241: Aluguel de equipamentos recreativos e esportivos
A242: 7722-5/00 | B242: Aluguel de fitas de vídeo, DVDs e Similares
A243: 7723-3/00 | B243: Aluguel de objetos do vestuário, joias e acessórios
A244: 7729-2/01 | B244: Aluguel de aparelhos de jogos eletrônicos
A245: 7729-2/02 | B245: Aluguel de móveis, utensílios e aparelhos de uso doméstico e pessoal; instrumentos musicais
A246: 7729-2/03 | B246: Aluguel de material médico
A247: 7729-2/99 | B247: Aluguel de outros objetos pessoais e domésticos não especificados anteriormente
A248: 7733-1/00 | B248: Aluguel de máquinas e equipamentos para escritório
A249: 7911-2/00 | B249: Agências de viagens
A250: 7912-1/00 | B250: Operadores turísticos
...

Sheet IN 003 VISA
B1: BAIXO RISCO (ANEXO I) | E1: MÉDIO RISCO (ANEXO II) | H1: ALTO RISCO (ANEXO III)
A2: Cód CNAE | B2: Denominação | D2: Cód CNAE | E2: Denominação | G2: Cód CNAE | H2: Denominação
A3: 0111-3/01 | B3: Cultivo de arroz | C3: =MATCH(A3,PRINCIPAL!A:A,0) -> 2 | D3: 1031-7/00 | E3: Fabricação de conservas de frutas | G3: 0892-4/03 | H3: Refino e outros tratamentos do sal
A4: 0111-3/02 | B4: Cultivo de milho | C4: =MATCH(A4,PRINCIPAL!A:A,0) -> 3 | D4: 1032-5/99 | E4: Fabricação de conservas de legumes e outros vegetais, exceto palmito | G4: 1032-5/01 | H4: Fabricação de conservas de palmito
A5: 0111-3/03 | B5: Cultivo de trigo | C5: =MATCH(A5,PRINCIPAL!A:A,0) -> 4 | D5: 1063-5/00 | E5: Fabricação de farinha de mandioca e derivados | G5: 1042-2/00 | H5: Fabricação de óleos vegetais refinados, exceto óleo de milho
A6: 0111-3/99 | B6: Cultivo de outros cereais não especificados anteriormente | C6: =MATCH(A6,PRINCIPAL!A:A,0) -> 5 | D6: 1064-3/00 | E6: Fabricação de farinha de milho e derivados, exceto óleos de milho | G6: 1053-8/00 | H6: Fabricação de sorvetes e outros gelados comestíveis
A7: 0112-1/01 | B7: Cultivo de algodão herbáceo | C7: =MATCH(A7,PRINCIPAL!A:A,0) -> 6 | D7: 1065-1/01 | E7: Fabricação de amidos e féculas de vegetais | G7: 1061-9/01 | H7: Beneficiamento de arroz
A8: 0112-1/02 | B8: Cultivo de juta | C8: =MATCH(A8,PRINCIPAL!A:A,0) -> 7 | D8: 1069-4/00 | E8: Moagem e fabricação de produtos de origem vegetal não especificados anteriormente | G8: 1061-9/02 | H8: Fabricação de produtos do arroz
A9: 0112-1/99 | B9: Cultivo de outras fibras de lavoura temporária não especificadas anteriormente | C9: =MATCH(A9,PRINCIPAL!A:A,0) -> 8 | D9: 1071-6/00 | E9: Fabricação de açúcar em bruto | G9: 1062-7/00 | H9: Moagem de trigo e fabricação de derivados
A10: 0113-0/00 | B10: Cultivo de cana-de-açúcar | C10: =MATCH(A10,PRINCIPAL!A:A,0) -> 9 | D10: 1072-4/01 | E10: Fabricação de açúcar de cana refinado | G10: 1065-1/03 | H10: Fabricação de óleo de milho refinado
A11: 0114-8/00 | B11: Cultivo de fumo | C11: =MATCH(A11,PRINCIPAL!A:A,0) -> 10 | D11: 1072-4/02 | E11: Fabricação de açúcar de cereais (dextrose) e de beterraba | G11: 1081-3/01 | H11: Beneficiamento de café
A12: 0115-6/00 | B12: Cultivo de soja | C12: =MATCH(A12,PRINCIPAL!A:A,0) -> 11 | D12: 1096-1/00 | E12: Fabricação de alimentos e pratos prontos | G12: 1081-3/02 | H12: Torrefação e moagem de café
A13: 0116-4/01 | B13: Cultivo de amendoim | C13: =MATCH(A13,PRINCIPAL!A:A,0) -> 12 | D13: 1099-6/05 | E13: Fabricação de produtos para infusão (chá, mate, etc.) | G13: 1082-1/00 | H13: Fabricação de produtos à base de café
A14: 0116-4/02 | B14: Cultivo de girassol | C14: =MATCH(A14,PRINCIPAL!A:A,0) -> 13 | D14: 3250-7/03 | E14: Fabricação de aparelhos e utensílios para correção de defeitos físicos e aparelhos ortopédicos em geral sob encomenda | G14: 1091-1/01 | H14: Fabricação de produtos de panificação industrial
... A82: 0162-8/99 | B82: Atividades de apoio à pecuária não especificadas anteriormente | C82: =MATCH(A82,PRINCIPAL!A:A,0) -> 81 | D82: 9609-2/05 | E82: Atividades de sauna e banhos | G82: 8640-2/11 | H82: Serviços de radioterapia
A83: 0163-6/00 | B83: Atividades de pós-colheita | C83: =MATCH(A83,PRINCIPAL!A:A,0) -> 82 | G83: 8640-2/12 | H83: Serviços de hemoterapia - inclusive bancos de
A84: 0170-9/00 | B84: Caça e serviços relacionados | C84: =MATCH(A84,PRINCIPAL!A:A,0) -> 83 | H84: sangue
A85: 0210-1/01 | B85: Cultivo de eucalipto | C85: =MATCH(A85,PRINCIPAL!A:A,0) -> 84 | G85: 8640-2/13 | H85: Serviços de litotripsia
A86: 0210-1/02 | B86: Cultivo de acácia-negra | C86: =MATCH(A86,PRINCIPAL!A:A,0) -> 85 | G86: 8640-2/14 | H86: Serviços de bancos de células e tecidos humanos - inclusive Centro de Terapia Celular
A87: 0210-1/03 | B87: Cultivo de pinus | C87: =MATCH(A87,PRINCIPAL!A:A,0) -> 86 | G87: 8640-2/99 | H87: Atividades de serviços de complementação diagnóstica e terapêutica não especificadas anteriormente
A88: 0210-1/04 | B88: Cultivo de teca | C88: =MATCH(A88,PRINCIPAL!A:A,0) -> 87 | G88: 8650-0/07 | H88: Atividades de terapia de nutrição enteral e parenteral
A89: 0210-1/05 | B89: Cultivo de espécies madeireiras, exceto eucalipto, acácia-negra, pinus e teca | C89: =MATCH(A89,PRINCIPAL!A:A,0) -> 88 | G89: 8650-0/99 | H89: Atividades de profissionais da área de saúde não especificadas anteriormente
A90: 0210-1/06 | B90: Cultivo de mudas em viveiros florestais | C90: =MATCH(A90,PRINCIPAL!A:A,0) -> 89 | G90: 8690-9/02 | H90: Atividades de Bancos de Leite Humano - inclusive posto de coleta
A91: 0210-1/07 | B91: Extração de madeira em florestas plantadas | C91: =MATCH(A91,PRINCIPAL!A:A,0) -> 90 | G91: 8690-9/99 | H91: Outras atividades de atenção à saúde humana não especificadas anteriormente
A92: 0210-1/08 | B92: Produção de carvão vegetal - florestas plantadas | C92: =MATCH(A92,PRINCIPAL!A:A,0) -> 91 | G92: 8711-5/01 | H92: Clínicas e residências geriátricas
A93: 0210-1/09 | B93: Produção de casca de acácia-negra - florestas plantadas | C93: =MATCH(A93,PRINCIPAL!A:A,0) -> 92 | G93: 8711-5/02 | H93: Instituições de longa permanência para idosos
A94: 0210-1/99 | B94: Produção de produtos não madeireiros não especificados anteriormente em florestas plantadas | C94: =MATCH(A94,PRINCIPAL!A:A,0) -> 93 | G94: 8711-5/05 | H94: Condomínios residenciais para idosos - Incluindo Centros de Atenção Diária e Centro de Convivência de Idosos
A95: 0220-9/01 | B95: Extração de madeira em florestas nativas | C95: =MATCH(A95,PRINCIPAL!A:A,0) -> 94 | G95: 8720-4/01 | H95: Atividades de centros de assistência psicossocial - CAPS AD, I, 1, 2, 3 ou 4
A96: 0220-9/02 | B96: Produção de carvão vegetal - florestas nativas | C96: =MATCH(A96,PRINCIPAL!A:A,0) -> 95 | G96: 8720-4/99 | H96: Atividades de assistência psicossocial e à saúde a portadores de distúrbios psíquicos, deficiência mental e dependência química e grupos similares não especificadas anteriormente - Incluindo Serviços Residenciais Terapêuticos em Saúde Mental, Comunidades Terapêuticas de Saúde e de Interesse da Saúde
... A100: 0220-9/06 | B100: Conservação de florestas nativas | C100: =MATCH(A100,PRINCIPAL!A:A,0) -> 99 | G100: 9609-2/06 | H100: Serviços de tatuagem e colocação de piercing
A101: 0220-9/99 | B101: Coleta de produtos não madeireiros não especificados anteriormente em florestas nativas | C101: =MATCH(A101,PRINCIPAL!A:A,0) -> 100
A102: 0230-6/00 | B102: Atividades de apoio à produção florestal | C102: =MATCH(A102,PRINCIPAL!A:A,0) -> 101
A103: 0311-6/01 | B103: Pesca de peixes em água salgada | C103: =MATCH(A103,PRINCIPAL!A:A,0) -> 102
A104: 0311-6/02 | B104: Pesca de crustáceos e moluscos em água salgada | C104: =MATCH(A104,PRINCIPAL!A:A,0) -> 103
A105: 0311-6/03 | B105: Coleta de outros produtos marinhos | C105: =MATCH(A105,PRINCIPAL!A:A,0) -> 104
A106: 0311-6/04 | B106: Atividades de apoio à pesca em água salgada | C106: =MATCH(A106,PRINCIPAL!A:A,0) -> 105
A107: 0312-4/01 | B107: Pesca de peixes em água doce | C107: =MATCH(A107,PRINCIPAL!A:A,0) -> 106
A108: 0312-4/02 | B108: Pesca de crustáceos e moluscos em água doce | C108: =MATCH(A108,PRINCIPAL!A:A,0) -> 107
A109: 0312-4/03 | B109: Coleta de outros produtos aquáticos de água doce | C109: =MATCH(A109,PRINCIPAL!A:A,0) -> 108
A110: 0312-4/04 | B110: Atividades de apoio à pesca em água doce | C110: =MATCH(A110,PRINCIPAL!A:A,0) -> 109
A111: 0321-3/01 | B111: Criação de peixes em água salgada e salobra | C111: =MATCH(A111,PRINCIPAL!A:A,0) -> 110
A112: 0321-3/02 | B112: Criação de camarões em água salgada e salobra | C112: =MATCH(A112,PRINCIPAL!A:A,0) -> 111
... A1096: 9900-8/00 | B1096: Organismos internacionais e outras instituições extraterritoriais | C1096: =MATCH(A1096,PRINCIPAL!A:A,0) -> 1338

Sheet Lista IMA
A1: CNAE | B1: Descrição da Atividade
A2: 0111-3/02 | B2: Cultivo de milho
A3: 0111-3/03 | B3: Cultivo de trigo
A4: 0111-3/99 | B4: Cultivo de outros cereais não especificados anteriormente
A5: 0112-1/01 | B5: Cultivo de algodão herbáceo
A6: 0112-1/02 | B6: Cultivo de juta
A7: 0112-1/99 | B7: Cultivo de outras fibras de lavoura temporária não especificadas anteriormente
A8: 0113-0/00 | B8: Cultivo de cana-de-açúcar
A9: 0114-8/00 | B9: Cultivo de fumo
A10: 0115-6/00 | B10: Cultivo de soja
A11: 0116-4/01 | B11: Cultivo de amendoim
A12: 0116-4/02 | B12: Cultivo de girassol
... A697: 9900-8/00 | B697: Organismos internacionais e outras instituições extraterritoriais
B699: Lista das Atividades Econômicas dispensadas sumariamente do licenciamento ambiental no Estado de Santa Catarina*
B700: *Esta listagem não substitui o texto da Portaria IMA nº 229, de 4 de novembro de 2019 (publicada no D.O.E. em 6 de novembro de 2019), e Portaria IMA nº 106, de 9 de junho de 2020 (publicada no D.O.E. em 10 de junho de 2020). Se a atividade estiver localizada em algum município habilitado ao licenciamento ambiental (consulte aqui), a Declaração de Atividade Não Constante deve ser solicitada junto ao órgão ambiental do município.

Sheet CNAES 2.3
A1: CNAES | B1: DESCRIÇÃO CNAES 2.3
A2: 0111-3/01 | B2: Cultivo de arroz | C2: =MATCH(A2,PRINCIPAL!A:A,0) -> 2
A3: 0111-3/02 | B3: Cultivo de milho | C3: =MATCH(A3,PRINCIPAL!A:A,0) -> 3
A4: 0111-3/03 | B4: Cultivo de trigo | C4: =MATCH(A4,PRINCIPAL!A:A,0) -> 4
A5: 0111-3/99 | B5: Cultivo de outros cereais não especificados anteriormente | C5: =MATCH(A5,PRINCIPAL!A:A,0) -> 5
A6: 0112-1/01 | B6: Cultivo de algodão herbáceo | C6: =MATCH(A6,PRINCIPAL!A:A,0) -> 6
A7: 0112-1/02 | B7: Cultivo de juta | C7: =MATCH(A7,PRINCIPAL!A:A,0) -> 7
A8: 0112-1/99 | B8: Cultivo de outras fibras de lavoura temporária não especificadas anteriormente | C8: =MATCH(A8,PRINCIPAL!A:A,0) -> 8
A9: 0113-0/00 | B9: Cultivo de cana-de-açúcar | C9: =MATCH(A9,PRINCIPAL!A:A,0) -> 9
A10: 0114-8/00 | B10: Cultivo de fumo | C10: =MATCH(A10,PRINCIPAL!A:A,0) -> 10
A11: 0115-6/00 | B11: Cultivo de soja | C11: =MATCH(A11,PRINCIPAL!A:A,0) -> 11
A12: 0116-4/01 | B12: Cultivo de amendoim | C12: =MATCH(A12,PRINCIPAL!A:A,0) -> 12
A13: 0116-4/02 | B13: Cultivo de girassol | C13: =MATCH(A13,PRINCIPAL!A:A,0) -> 13
... A1332: 9700-5/00 | B1332: Serviços domésticos | C1332: =MATCH(A1332,PRINCIPAL!A:A,0) -> 1337

Sheet Antiga
A1: CNAE | B1: Descrição | C1: Exceções / Restrições / Condicionantes
A2: 1311-1/00 | B2: Preparação e fiação de fibras de algodão. | D2: =MATCH(A2,PRINCIPAL!A:A,0) -> 241
A3: 1312-0/00 | B3: Preparação e fiação de fibras têxteis naturais, exceto algodão. | D3: =MATCH(A3,PRINCIPAL!A:A,0) -> 242
A4: 1340-5/99 | B4: Outros serviços de acabamento em fios, tecidos, artefatos têxteis e peças do vestuário. | D4: =MATCH(A4,PRINCIPAL!A:A,0) -> 251
A5: 1351-1/00 | B5: Fabricação de artefatos têxteis para uso doméstico. | D5: =MATCH(A5,PRINCIPAL!A:A,0) -> 252
A6: 1354-5/00 | B6: Fabricação de tecidos especiais, inclusive artefatos, desde que a área construída do empreendimento não ultrapasse 2.500m² (dois mil e quinhentos metros quadrados). | D6: =MATCH(A6,PRINCIPAL!A:A,0) -> 255
A7: 1359-6/00 | B7: Fabricação de outros produtos têxteis não especificados anteriormente. | D7: =MATCH(A7,PRINCIPAL!A:A,0) -> 256
A8: 1521-1/00 | B8: Fabricação de artigos para viagem, bolsas e semelhantes de qualquer material. | C8: desde que a área construída do empreendimento não ultrapasse 2.500m² (dois mil e quinhentos metros quadrados). | D8: =MATCH(A8,PRINCIPAL!A:A,0) -> 269
A9: 1529-7/00 | B9: Fabricação de artefatos de couro não especificados anteriormente. | D9: =MATCH(A9,PRINCIPAL!A:A,0) -> 270
A10: 1531-9/01 | B10: Fabricação de calçados de couro, desde que a área construída do empreendimento não ultrapasse 2.500m² (dois mil e quinhentos metros quadrados). | D10: =MATCH(A10,PRINCIPAL!A:A,0) -> 271
A11: 2319-2/00 | B11: Fabricação de artigos de vidro. | C11: Exceto destinados para alimentos e bebidas. | D11: =MATCH(A11,PRINCIPAL!A:A,0) -> 367
A12: 2399-1/01 | B12: Decoração, lapidação, gravação, vitrificação e outros trabalhos em cerâmica, louça, vidro e cristal. | D12: =MATCH(A12,PRINCIPAL!A:A,0) -> 384
A13: 3291-4/00 | B13: Fabricação de escovas, pincéis e vassouras. | C13: Exceto escovas de dente. | D13: =MATCH(A13,PRINCIPAL!A:A,0) -> 542
A14: 3299-0/06 | B14: Fabricação de velas, inclusive decorativas, desde que não haja, no exercício da atividade, a fabricação de velas, sebo e/ou estearina utilizadas como cosmético ou saneante. | D14: =MATCH(A14,PRINCIPAL!A:A,0) -> 550
A15: 3312-1/02 | B15: Manutenção e reparação de aparelhos e instrumentos de medida, teste e controle. | D15: =MATCH(A15,PRINCIPAL!A:A,0) -> 553
A16: 3312-1/04 | B16: Manutenção e reparação de equipamentos e instrumentos ópticos. | D16: =MATCH(A16,PRINCIPAL!A:A,0) -> 555
A17: 4520-0/03 | B17: Serviços de manutenção e reparação elétrica de veículos automotores. | D17: =MATCH(A17,PRINCIPAL!A:A,0) -> 670
A18: 4520-0/04 | B18: Serviços de alinhamento e balanceamento de veículos automotores. | D18: =MATCH(A18,PRINCIPAL!A:A,0) -> 671
A19: 4520-0/05 | B19: Serviços de lavagem, lubrificação e polimento de veículos automotores. | D19: =MATCH(A19,PRINCIPAL!A:A,0) -> 672
A20: 4520-0/07 | B20: Serviços de instalação, manutenção e reparação de acessórios para veículos automotores. | D20: =MATCH(A20,PRINCIPAL!A:A,0) -> 674
A21: 4541-2/06 | B21: Comércio a varejo de peças e acessórios para motocicletas e motonetas. | D21: =MATCH(A21,PRINCIPAL!A:A,0) -> 687
A22: 4641-9/01 | B22: Comércio atacadista de tecidos. | D22: =MATCH(A22,PRINCIPAL!A:A,0) -> 743
A23: 4641-9/02 | B23: Comércio atacadista de artigos de cama, mesa e banho. | D23: =MATCH(A23,PRINCIPAL!A:A,0) -> 744
A24: 4641-9/03 | B24: Comércio atacadista de artigos de armarinho. | D24: =MATCH(A24,PRINCIPAL!A:A,0) -> 745
A25: 4642-7/01 | B25: Comércio atacadista de artigos do vestuário e acessórios, exceto profissionais e de segurança. | D25: =MATCH(A25,PRINCIPAL!A:A,0) -> 746
... A39: 4686-9/01 | B39: Comércio atacadista de papel e papelão em bruto. | D39: =MATCH(A39,PRINCIPAL!A:A,0) -> 800
A40: 4686-9/02 | B40: Comércio atacadista de embalagens. | C40: Exceto para alimentos ou bebidas. | D40: =MATCH(A40,PRINCIPAL!A:A,0) -> 801
A41: 4687-7/01 | B41: Comércio atacadista de resíduos de papel e papelão. | D41: =MATCH(A41,PRINCIPAL!A:A,0) -> 802
A42: 4687-7/03 | B42: Comércio atacadista de resíduos e sucatas metálicos. | D42: =MATCH(A42,PRINCIPAL!A:A,0) -> 804
A43: 4689-3/02 | B43: Comércio atacadista de fios e fibras beneficiados. | D43: =MATCH(A43,PRINCIPAL!A:A,0) -> 806
A44: 4692-3/00 | B44: Comércio atacadista de mercadorias em geral, com predominância de insumos agropecuários. | D44: =MATCH(A44,PRINCIPAL!A:A,0) -> 809
A45: 5232-0/00 | B45: Atividades de agenciamento marítimo. | D45: =MATCH(A45,PRINCIPAL!A:A,0) -> 944
A46: 5811-5/00 | B46: Edição de livros. | D46: =MATCH(A46,PRINCIPAL!A:A,0) -> 975
A47: 5812-3/01 | B47: Edição de jornais diários. | D47: =MATCH(A47,PRINCIPAL!A:A,0) -> 976
A48: 5812-3/02 | B48: Edição de jornais não diários. | D48: =MATCH(A48,PRINCIPAL!A:A,0) -> 977
A49: 5813-1/00 | B49: Edição de revistas. | D49: =MATCH(A49,PRINCIPAL!A:A,0) -> 978
A50: 5819-1/00 | B50: Edição de cadastros, listas e outros produtos gráficos. | D50: =MATCH(A50,PRINCIPAL!A:A,0) -> 979
A51: 7120-1/00 | B51: Testes e análises técnicas. | C51: Exceto Laboratórios Analíticos para análise de produtos sujeitos à vigilância sanitária. | D51: =MATCH(A51,PRINCIPAL!A:A,0) -> 1107
A52: 7490-1/03 | B52: Serviços de agronomia e de consultoria às atividades agrícolas e pecuárias. | D52: =MATCH(A52,PRINCIPAL!A:A,0) -> 1128
A53: 7500-1/00 | B53: Atividades veterinárias. | C53: Que NÃO utilizem medicamentos ou equipamentos de saúde humana. | D53: =MATCH(A53,PRINCIPAL!A:A,0) -> 1132
A54: 8292-0/00 | B54: Envasamento e empacotamento sob contrato. | C54: Exceto para medicamentos, insumos farmacêuticos, produtos para saúde, cosméticos, saneantes e alimentos. | D54: =MATCH(A54,PRINCIPAL!A:A,0) -> 1178
A55: 9319-1/01 | B55: Produção e promoção de eventos esportivos. | D55: =MATCH(A55,PRINCIPAL!A:A,0) -> 1292
A56: 9329-8/03 | B56: Exploração de jogos de sinuca, bilhar e similares. | D56: =MATCH(A56,PRINCIPAL!A:A,0) -> 1297
A57: 9329-8/04 | B57: Exploração de jogos eletrônicos recreativos. | D57: =MATCH(A57,PRINCIPAL!A:A,0) -> 1298
A58: 4614-1/00 | B58: Representantes comerciais e agentes do comércio de máquinas, equipamentos, embarcações e aeronaves. | D58: =MATCH(A58,PRINCIPAL!A:A,0) -> 695
A59: 4615-0/00 | B59: Representantes comerciais e agentes do comércio de eletrodomésticos, móveis e artigos de uso doméstico. | D59: =MATCH(A59,PRINCIPAL!A:A,0) -> 696
A60: 4616-8/00 | B60: Representantes comerciais e agentes do comércio de têxteis, vestuário, calçados e artigos de viagem. | D60: =MATCH(A60,PRINCIPAL!A:A,0) -> 697
A61: 4617-6/00 | B61: Representantes comerciais e agentes do comércio de produtos alimentícios, bebidas e fumo. | D61: =MATCH(A61,PRINCIPAL!A:A,0) -> 698
A62: 4618-4/01 | B62: Representantes comerciais e agentes do comércio de medicamentos, cosméticos e produtos de perfumaria. | D62: =MATCH(A62,PRINCIPAL!A:A,0) -> 699
A63: 4618-4/02 | B63: Representantes comerciais e agentes do comércio de instrumentos e materiais odonto-médico-hospitalares. | D63: =MATCH(A63,PRINCIPAL!A:A,0) -> 700
A64: 4618-4/03 | B64: Representantes comerciais e agentes do comércio de jornais, revistas e outras publicações. | D64: =MATCH(A64,PRINCIPAL!A:A,0) -> 701
A65: 4618-4/99 | B65: Outros representantes comerciais e agentes do comércio especializado em produtos não especificados anteriormente. | D65: =MATCH(A65,PRINCIPAL!A:A,0) -> 702
A66: 4619-2/00 | B66: Representantes comerciais e agentes do comércio de mercadorias em geral não especializado. | D66: =MATCH(A66,PRINCIPAL!A:A,0) -> 703
... A84: 4686-9/01 | B84: Comércio atacadista de papel e papelão em bruto. | D84: =MATCH(A84,PRINCIPAL!A:A,0) -> 800
A85: 4686-9/02 | B85: Comércio atacadista de embalagens. | C85: Exceto para alimentos ou bebidas. | D85: =MATCH(A85,PRINCIPAL!A:A,0) -> 801
A86: 4687-7/01 | B86: Comércio atacadista de resíduos de papel e papelão. | D86: =MATCH(A86,PRINCIPAL!A:A,0) -> 802
A87: 4687-7/03 | B87: Comércio atacadista de resíduos e sucatas metálicos. | D87: =MATCH(A87,PRINCIPAL!A:A,0) -> 804
A88: 4689-3/02 | B88: Comércio atacadista de fios e fibras beneficiados. | D88: =MATCH(A88,PRINCIPAL!A:A,0) -> 806
A89: 4692-3/00 | B89: Comércio atacadista de mercadorias em geral, com predominância de insumos agropecuários. | D89: =MATCH(A89,PRINCIPAL!A:A,0) -> 809
A90: 4741-5/00 | B90: Comércio varejista de tintas e materiais para pintura. | D90: =MATCH(A90,PRINCIPAL!A:A,0) -> 830
A91: 4742-3/00 | B91: Comércio varejista de material elétrico. | D91: =MATCH(A91,PRINCIPAL!A:A,0) -> 831
A92: 4743-1/00 | B92: Comércio varejista de vidros. | D92: =MATCH(A92,PRINCIPAL!A:A,0) -> 832
A93: 4744-0/01 | B93: Comércio varejista de ferragens e ferramentas. | D93: =MATCH(A93,PRINCIPAL!A:A,0) -> 833
A94: 4744-0/03 | B94: Comércio varejista de materiais hidráulicos. | D94: =MATCH(A94,PRINCIPAL!A:A,0) -> 835
A95: 4744-0/06 | B95: Comércio varejista de pedras para revestimento. | D95: =MATCH(A95,PRINCIPAL!A:A,0) -> 838
A96: 4744-0/99 | B96: Comércio varejista de materiais de construção em geral. | D96: =MATCH(A96,PRINCIPAL!A:A,0) -> 839
A97: 4751-2/01 | B97: Comércio varejista especializado de equipamentos e suprimentos de informática. | D97: =MATCH(A97,PRINCIPAL!A:A,0) -> 840
... A120: 4771-7/04 | B120: Comércio varejista de medicamentos veterinários. | D120: =MATCH(A120,PRINCIPAL!A:A,0) -> 866
A121: 4774-1/00 | B121: Comércio varejista de artigos de óptica. | C121: Exceto Lentes de Grau. | D121: =MATCH(A121,PRINCIPAL!A:A,0) -> 869
A122: 4781-4/00 | B122: Comércio varejista de artigos do vestuário e acessórios. | D122: =MATCH(A122,PRINCIPAL!A:A,0) -> 870
A123: 4782-2/01 | B123: Comércio varejista de calçados. | D123: =MATCH(A123,PRINCIPAL!A:A,0) -> 871
A124: 4782-2/02 | B124: Comércio varejista de artigos de viagem. | D124: =MATCH(A124,PRINCIPAL!A:A,0) -> 872
A125: 4783-1/01 | B125: Comércio varejista de artigos de joalheria. | D125: =MATCH(A125,PRINCIPAL!A:A,0) -> 873
A126: 4783-1/02 | B126: Comércio varejista de artigos de relojoaria. | D126: =MATCH(A126,PRINCIPAL!A:A,0) -> 874
A127: 4785-7/01 | B127: Comércio varejista de antigüidades. | D127: =MATCH(A127,PRINCIPAL!A:A,0) -> 876
A128: 4785-7/99 | B128: Comércio varejista de outros artigos usados. | D128: =MATCH(A128,PRINCIPAL!A:A,0) -> 877
A129: 4789-0/01 | B129: Comércio varejista de suvenires, bijuterias e artesanatos. | D129: =MATCH(A129,PRINCIPAL!A:A,0) -> 878
A130: 4789-0/02 | B130: Comércio varejista de plantas e flores naturais. | D130: =MATCH(A130,PRINCIPAL!A:A,0) -> 879
A131: 4789-0/03 | B131: Comércio varejista de objetos de arte. | D131: =MATCH(A131,PRINCIPAL!A:A,0) -> 880
A132: 4789-0/04 | B132: Comércio varejista de animais vivos e de artigos e alimentos para animais de estimação. | D132: =MATCH(A132,PRINCIPAL!A:A,0) -> 881
A133: 4789-0/07 | B133: Comércio varejista de equipamentos para escritório. | D133: =MATCH(A133,PRINCIPAL!A:A,0) -> 884
... A147: 6202-3/00 | B147: Desenvolvimento e licenciamento de programas de computador customizáveis. | D147: =MATCH(A147,PRINCIPAL!A:A,0) -> 1014
A148: 6203-1/00 | B148: Desenvolvimento e licenciamento de programas de computador não customizáveis. | C148: Exceto Produtos para Saúde. | D148: =MATCH(A148,PRINCIPAL!A:A,0) -> 1015
A149: 6204-0/00 | B149: Consultoria em tecnologia da informação. | D149: =MATCH(A149,PRINCIPAL!A:A,0) -> 1016
A150: 6209-1/00 | B150: Suporte técnico, manutenção e outros serviços em tecnologia da informação. | D150: =MATCH(A150,PRINCIPAL!A:A,0) -> 1017
A151: 6311-9/00 | B151: Tratamento de dados, provedores de serviços de aplicação e serviços de hospedagem na internet. | D151: =MATCH(A151,PRINCIPAL!A:A,0) -> 1018
A152: 6319-4/00 | B152: Portais, provedores de conteúdo e outros serviços de informação na internet. | D152: =MATCH(A152,PRINCIPAL!A:A,0) -> 1019
A153: 6391-7/00 | B153: Agências de notícias. | D153: =MATCH(A153,PRINCIPAL!A:A,0) -> 1020
A154: 6511-1/02 | B154: Planos de auxílio-funeral. | D154: =MATCH(A154,PRINCIPAL!A:A,0) -> 1059
A155: 6621-5/01 | B155: Peritos e avaliadores de seguros. | D155: =MATCH(A155,PRINCIPAL!A:A,0) -> 1082
A156: 6621-5/02 | B156: Auditoria e consultoria atuarial. | D156: =MATCH(A156,PRINCIPAL!A:A,0) -> 1083
A157: 6810-2/01 | B157: Compra e venda de imóveis próprios. | D157: =MATCH(A157,PRINCIPAL!A:A,0) -> 1087
A158: 6810-2/02 | B158: Aluguel de imóveis próprios. | D158: =MATCH(A158,PRINCIPAL!A:A,0) -> 1088
A159: 6821-8/01 | B159: Corretagem na compra e venda e avaliação de imóveis. | D159: =MATCH(A159,PRINCIPAL!A:A,0) -> 1090
A160: 6821-8/02 | B160: Corretagem no aluguel de imóveis. | D160: =MATCH(A160,PRINCIPAL!A:A,0) -> 1091
... A172: 7119-7/99 | B172: Atividades técnicas relacionadas à engenharia e arquitetura não especificadas anteriormente. | D172: =MATCH(A172,PRINCIPAL!A:A,0) -> 1106
A173: 7120-1/00 | B173: Testes e análises técnicas. | C173: Exceto Laboratórios Analíticos para análise de produtos sujeitos à vigilância sanitária. | D173: =MATCH(A173,PRINCIPAL!A:A,0) -> 1107
A174: 7210-0/00 | B174: Pesquisa e desenvolvimento experimental em ciências físicas e naturais. | D174: =MATCH(A174,PRINCIPAL!A:A,0) -> 1108
A175: 7220-7/00 | B175: Pesquisa e desenvolvimento experimental em ciências sociais e humanas. | D175: =MATCH(A175,PRINCIPAL!A:A,0) -> 1109
A176: 7311-4/00 | B176: Agências de publicidade. | D176: =MATCH(A176,PRINCIPAL!A:A,0) -> 1110
...

Sheet Atividades
B1: MEI | F1: OUTROS
A2: CNAE | B2: OCUPAÇÃO | C2: Restrição que deve constar no objeto social, para a liberação do Alvará de Licença de Atividade | E2: CNAE | F2: DESCRIÇÃO SUBCLASSE CNAE | G2: Restrição que deve constar no objeto social, para a liberação do Alvará de Licença de Atividade
A3: 1412-6/01 | B3: COSTUREIRO(A) DE ROUPAS, EXCETO SOB MEDIDA | C3: EXCLUSIVAMENTE NO CLIENTE / SEM DEPÓSITO DE MATERIAIS E MERCADORIAS | E3: 3321-0/00 | F3: INSTALAÇÃO E MONTAGEM DE APARELHOS E EQUIPAMENTOS DE IRRADIAÇÃO ELETROMÉDICOS E ELETROTERAPÊUTICOS | G3: EXCLUSIVAMENTE NO CLIENTE
A4: 1412-6/02 | B4: COSTUREIRO(A) DE ROUPAS, SOB MEDIDA | C4: EXCLUSIVAMENTE NO CLIENTE / SEM DEPÓSITO DE MATERIAIS E MERCADORIAS | E4: 3321-0/00 | F4: INSTALAÇÃO E MONTAGEM DE EQUIPAMENTOS E INSTRUMENTOS DE MEDIDA, TESTE E CONTROLE | G4: EXCLUSIVAMENTE NO CLIENTE
A5: 3314-7/01 | B5: REPARADOR(A) DE MÁQUINAS MOTRIZES NÃO-ELÉTRICAS | C5: EXCLUSIVAMENTE NO CLIENTE | E5: 3321-0/00 | F5: INSTALAÇÃO E MONTAGEM DE GERADORES, TRANSFORMADORES, MOTORES E OUTROS EQUIPAMENTOS ELÉTRICOS | G5: EXCLUSIVAMENTE NO CLIENTE
A6: 3314-7/06 | B6: REPARADOR(A) DE MÁQUINAS, APARELHOS E EQUIPAMENTOS PARA INSTALAÇÕES TÉRMICAS | C6: EXCLUSIVAMENTE NO CLIENTE | E6: 3321-0/00 | F6: INSTALAÇÃO E MONTAGEM DE MÁQUINAS E EQUIPAMENTOS PARA INDUSTRIA DO PLÁSTICO | G6: EXCLUSIVAMENTE NO CLIENTE
A7: 3314-7/07 | B7: REPARADOR(A) DE MÁQUINAS E APARELHOS DE REFRIGERAÇÃO E VENTILAÇÃO PARA USO INDUSTRIAL E COMERCIAL | C7: EXCLUSIVAMENTE NO CLIENTE | E7: 3321-0/00 | F7: INSTALAÇÃO E MONTAGEM DE MÁQUINAS E EQUIPAMENTOS PARA INDUSTRIA TÊXTIL, DO VESTUÁRIO, COURO E CALÇADOS | G7: EXCLUSIVAMENTE NO CLIENTE
A8: 3314-7/10 | B8: REPARADOR(A) DE MÁQUINAS PARA BARES E LANCHONETES | C8: EXCLUSIVAMENTE NO CLIENTE | E8: 3321-0/00 | F8: INSTALAÇÃO E MONTAGEM DE MÁQUINAS E EQUIPAMENTOS PARA TERRAPLENAGEM, PAVIMENTAÇÃO E CONSTRUÇÃO | G8: EXCLUSIVAMENTE NO CLIENTE
A9: 3314-7/11 | B9: REPARADOR(A) DE MÁQUINAS E EQUIPAMENTOS PARA AGRICULTURA E PECUÁRIA | C9: EXCLUSIVAMENTE NO CLIENTE | E9: 3321-0/00 | F9: INSTALAÇÃO E MONTAGEM DE MÁQUINAS E EQUIPAMENTOS PARA USO AGRÍCOLA | G9: EXCLUSIVAMENTE NO CLIENTE
A10: 3314-7/12 | B10: REPARADOR(A) DE TRATORES AGRÍCOLAS | C10: EXCLUSIVAMENTE NO CLIENTE | E10: 3321-0/00 | F10: INSTALAÇÃO E MONTAGEM DE MÁQUINAS E EQUIPAMENTOS PARA USO GERAL | G10: EXCLUSIVAMENTE NO CLIENTE
A11: 3314-7/19 | B11: REPARADOR(A) DE MÁQUINAS E EQUIPAMENTOS PARA AS INDÚSTRIAS DE ALIMENTOS, BEBIDAS E FUMO | C11: EXCLUSIVAMENTE NO CLIENTE | E11: 3321-0/00 | F11: INSTALAÇÃO E MONTAGEM DE MÁQUINAS E EQUIPAMENTOS PARA USO NA EXTRAÇÃO MINERAL, | G11: EXCLUSIVAMENTE NO CLIENTE
A12: 3314-7/20 | B12: REPARADOR(A) DE MÁQUINAS E EQUIPAMENTOS PARA A INDÚSTRIA TÊXTIL, DO VESTUÁRIO, DO COURO E CALÇADOS | C12: EXCLUSIVAMENTE NO CLIENTE | E12: 3321-0/00 | F12: INSTALAÇÃO E MONTAGEM DE MÁQUINAS E EQUIPAMENTOS PARA USOS INDUSTRIAIS ESPECÍFICO | G12: EXCLUSIVAMENTE NO CLIENTE
A13: 3314-7/99 | B13: REPARADOR(A) DE MÁQUINAS E APARELHOS PARA A INDÚSTRIA GRÁFICA | C13: EXCLUSIVAMENTE NO CLIENTE | E13: 3321-0/00 | F13: INSTALAÇÃO E MONTAGEM DE MÁQUINAS-FERRAMENTA | G13: EXCLUSIVAMENTE NO CLIENTE
... A23: 4322-3/01 | B23: BOMBEIRO(A) HIDRÁULICO | C23: EXCLUSIVAMENTE NO CLIENTE | E23: 3329-5/01 | F23: MONTAGEM DE MOVEIS DE QUALQUER MATERIAL PARA CONSUMIDOR FINAL, NÃO ASSOCIADA AO COMÉRCIO, QUANDO EXECUTADA POR UNIDADE ESPECIALIZADA | G23: EXCLUSIVAMENTE NO CLIENTE
A24: 4322-3/01 | B24: ENCANADOR | C24: EXCLUSIVAMENTE NO CLIENTE | E24: 4110-7/00 | F24: INCORPORAÇÃO DE IMÓVEIS POR CONTA PRÓPRIA
A25: 4322-3/02 | B25: INSTALADOR(A) E REPARADOR(A) DE SISTEMAS CENTRAIS DE AR CONDICIONADO, DE VENTILAÇÃO E REFRIGERAÇÃO | C25: EXCLUSIVAMENTE NO CLIENTE | E25: 4110-7/00 | F25: INCORPORAÇÃO DE IMÓVEIS PRÓPRIOS
A26: 4322-3/03 | B26: INSTALADOR(A) DE SISTEMA DE PREVENÇÃO CONTRA INCÊNDIO | C26: EXCLUSIVAMENTE NO CLIENTE | E26: 4321-5/00 | F26: CONSTRUÇÃO E MANUTENÇÃO DE INSTALAÇÕES PARA CENTRO DE PROCESSAMENTO DE DADOS | G26: EXCLUSIVAMENTE NO CLIENTE
A27: 4329-1/01 | B27: INSTALADOR(A) DE PAINÉIS PUBLICITÁRIOS | C27: EXCLUSIVAMENTE NO CLIENTE / SEM DEPÓSITO DE MATERIAIS E MERCADORIAS | E27: 4321-5/00 | F27: CPD, CONSTRUÇÃO E MANUTENÇÃO DE INSTALAÇÕES | G27: EXCLUSIVAMENTE NO CLIENTE
A28: 4329-1/02 | B28: INSTALADOR(A) DE EQUIPAMENTOS PARA ORIENTAÇÃO À NAVEGAÇÃO MARÍTIMA, FLUVIAL E LACUSTRE | C28: EXCLUSIVAMENTE NO CLIENTE | E28: 4321-5/00 | F28: INSTALAÇÃO DE ALARME CONTRA ROUBO EM EDIFICAÇÕES | G28: EXCLUSIVAMENTE NO CLIENTE
A29: 4329-1/03 | B29: INSTALADOR(A) E REPARADOR(A) DE ELEVADORES, ESCADAS E ESTEIRAS ROLANTES | C29: EXCLUSIVAMENTE NO CLIENTE | E29: 4321-5/00 | F29: INSTALAÇÃO DE ANTENAS COLETIVAS E PARABÓLICAS | G29: EXCLUSIVAMENTE NO CLIENTE
A30: 4329-1/05 | B30: INSTALADOR(A) DE ISOLANTES ACÚSTICOS E DE VIBRAÇÃO | C30: EXCLUSIVAMENTE NO CLIENTE | E30: 4321-5/00 | F30: INSTALAÇÃO DE ANTENAS DE TELEVISÃO | G30: EXCLUSIVAMENTE NO CLIENTE
A31: 4329-1/05 | B31: INSTALADOR(A) DE ISOLANTES TÉRMICOS | C31: EXCLUSIVAMENTE NO CLIENTE | E31: 4321-5/00 | F31: INSTALAÇÃO DE CABEAÇÃO LÓGICA | G31: EXCLUSIVAMENTE NO CLIENTE
A32: 4330-4/02 | B32: CARPINTEIRO(A) INSTALADOR(A) | C32: EXCLUSIVAMENTE NO CLIENTE | E32: 4321-5/00 | F32: INSTALAÇÃO DE CABOS PARA INSTALAÇÕES DE COMUNICAÇÃO E INFORMÁTICA EM EDIFICAÇÕES | G32: EXCLUSIVAMENTE NO CLIENTE
A33: 4330-4/03 | B33: GESSEIRO(A) | C33: EXCLUSIVAMENTE NO CLIENTE / SEM DEPÓSITO DE MATERIAL | E33: 4321-5/00 | F33: INSTALAÇÃO DE CABOS PARA INSTALAÇÕES TELEFÔNICAS EM EDIFICAÇÕES | G33: EXCLUSIVAMENTE NO CLIENTE
A34: 4330-4/04 | B34: PINTOR(A) DE PAREDE | C34: EXCLUSIVAMENTE NO CLIENTE / SEM DEPÓSITO DE MATERIAL | E34: 4321-5/00 | F34: INSTALAÇÃO DE CABOS PARA TELEVISÃO EM EDIFICAÇÕES | G34: EXCLUSIVAMENTE NO CLIENTE
A35: 4330-4/05 | B35: AZULEJISTA | C35: EXCLUSIVAMENTE NO CLIENTE / SEM DEPÓSITO DE MATERIAL | E35: 4321-5/00 | F35: INSTALAÇÃO DE CAIXAS DE ENTRADA DE ENERGIA EM EDIFICAÇÕES | G35: EXCLUSIVAMENTE NO CLIENTE
A36: 4330-4/05 | B36: CALAFETADOR(A) | C36: EXCLUSIVAMENTE NO CLIENTE / SEM DEPÓSITO DE MATERIAL | E36: 4321-5/00 | F36: INSTALAÇÃO DE EQUIPAMENTOS DE INTERCOMUNICAÇÃO EM EDIFICAÇÕES | G36: EXCLUSIVAMENTE NO CLIENTE
A37: 4330-4/05 | B37: COLOCADOR(A) DE REVESTIMENTOS | C37: EXCLUSIVAMENTE NO CLIENTE / SEM DEPÓSITO DE MATERIAL | E37: 4321-5/00 | F37: INSTALAÇÃO DE PADRÃO DE ENERGIA (CAIXAS, QUADROS, PAINÉIS OU CUBÍCULOS) | G37: EXCLUSIVAMENTE NO CLIENTE
... A45: 4772-5/00 | B45: COMERCIANTE DE COSMÉTICOS E ARTIGOS DE PERFUMARIA | C45: EXCLUSIVAMENTE NO CLIENTE / SEM ESTOQUE | E45: 4321-5/00 | F45: INSTALAÇÃO DE SISTEMAS DE ELETRICIDADE (CABOS DE QUALQUER TENSÃO, FIAÇÃO, MATERIAIS ELÉTRICOS) | G45: EXCLUSIVAMENTE NO CLIENTE
A46: 4923-0/01 | B46: MOTOTAXISTA | E46: 4321-5/00 | F46: INSTALAÇÃO DE SISTEMAS ELÉTRICOS EM EDIFICAÇÕES | G46: EXCLUSIVAMENTE NO CLIENTE
A47: 4924-8/00 | B47: TRANSPORTADOR(A) ESCOLAR INDEPENDENTE | C47: NÃO UTILIZAR VIA PÚBLICA COMO LOCAL DE GUARDA DO VEÍCULO QUANDO O MESMO NÃO ESTIVER EM SERVIÇO. | E47: 4321-5/00 | F47: INSTALAÇÃO E MANUTENÇÃO DE AUTOMAÇÃO PREDIAL | G47: EXCLUSIVAMENTE NO CLIENTE
A48: 4929-9/01 | B48: TRANSPORTADOR(A) MUNICIPAL DE PASSAGEIROS SOB FRETE INDEPENDENTE | C48: NÃO UTILIZAR VIA PÚBLICA COMO LOCAL DE GUARDA DO VEÍCULO QUANDO O MESMO NÃO ESTIVER EM SERVIÇO. | E48: 4321-5/00 | F48: INSTALAÇÃO E MANUTENÇÃO DE CABOS ELÉTRICOS EM EDIFICAÇÕES | G48: EXCLUSIVAMENTE NO CLIENTE
A49: 4929-9/02 | B49: TRANSPORTADOR(A) INTERMUNICIPAL DE PASSAGEIROS SOB FRETE EM REGIÃO METROPOLITANA INDEPENDENTE | C49: NÃO UTILIZAR VIA PÚBLICA COMO LOCAL DE GUARDA DO VEÍCULO QUANDO O MESMO NÃO ESTIVER EM SERVIÇO | E49: 4321-5/00 | F49: MANUTENÇÃO DE INSTALAÇÕES PARA ANTENAS COLETIVAS E PARABÓLICAS | G49: EXCLUSIVAMENTE NO CLIENTE
A50: 4929-9/03 | B50: ORGANIZADOR(A) DE EXCURSÕES EM VEÍCULO PRÓPRIO, MUNICIPAL | E50: 4321-5/00 | F50: MANUTENÇÃO DE INSTALAÇÕES PARA PÁRA-RAIOS | G50: EXCLUSIVAMENTE NO CLIENTE
A51: 4929-9/03 | B51: ORGANIZADOR(A) DE EXCURSÕES EM VEÍCULO PRÓPRIO, MUNICIPAL INDEPENDENTE | C51: NÃO UTILIZAR VIA PÚBLICA COMO LOCAL DE GUARDA DO VEÍCULO QUANDO O MESMO NÃO ESTIVER EM SERVIÇO | E51: 4321-5/00 | F51: MANUTENÇÃO DE INSTALAÇÕES PARA PORTÃO ELETRÔNICO | G51: EXCLUSIVAMENTE NO CLIENTE
A52: 5212-5/00 | B52: CARREGADOR (VEÍCULOS DE TRANSPORTES TERRESTRES) | C52: EXCLUSIVAMENTE NO CLIENTE | E52: 4321-5/00 | F52: MANUTENÇÃO DE INSTALAÇÕES PARA SISTEMA DE ALARMES CONTRA ROUBOS EM EDIFICAÇÕES | G52: EXCLUSIVAMENTE NO CLIENTE
A53: 5229-0/02 | B53: GUINCHEIRO (REBOQUE DE VEÍCULOS) | C53: EXCLUSIVAMENTE NO CLIENTE / SEM DEPÓSITO PARA VEÍCULOS | E53: 4321-5/00 | F53: MANUTENÇÃO DE PÁRA-RAIOS | G53: EXCLUSIVAMENTE NO CLIENTE
A54: 5320-2/01 | B54: ENTREGADOR DE MALOTES | C54: EXCLUSIVAMENTE NO CLIENTE / SEM DEPÓSITO DE MATERIAIS | E54: 4321-5/00 | F54: MANUTENÇÃO DE PORTÃO ELETRÔNICO | G54: EXCLUSIVAMENTE NO CLIENTE
A55: 5320-2/02 | B55: BIKEBOY (CICLISTA MENSAGEIRO) | C55: EXCLUSIVAMENTE NO CLIENTE / SEM DEPÓSITO DE MATERIAIS / EXCETO MEDICAMENTOS | E55: 4321-5/00 | F55: MANUTENÇÃO DE SISTEMAS DE ALARMES CONTRA ROUBO EM EDIFICAÇÕES | G55: EXCLUSIVAMENTE NO CLIENTE
A56: 5320-2/02 | B56: MOTOBOY | E56: 4321-5/00 | F56: OBRAS DE INSTALAÇÃO, MANUTENÇÃO E REPARAÇÃO CABOS PARA INSTALAÇÕES TELEFÔNICAS, INFORMÁTICAS E COMUNICAÇÕES EM EDIFICAÇÕES DE QUALQUER TIPO | G56: EXCLUSIVAMENTE NO CLIENTE
A57: 5811-5/00 | B57: EDITOR(A) DE LIVROS | C57: EXCLUSIVAMENTE NO CLIENTE / EXERCIDAS PELA INTERNET / COM IMPRESSÃO TERCEIRIZADA | E57: 4321-5/00 | F57: OBRAS DE INSTALAÇÕES PARA ELETRIFICAÇÃO RURAL | G57: EXCLUSIVAMENTE NO CLIENTE
A58: 5812-3/01 | B58: EDITOR(A) DE JORNAIS DIÁRIOS | C58: EXCLUSIVAMENTE NO CLIENTE / EXERCIDAS PELA INTERNET / COM IMPRESSÃO TERCEIRIZADA | E58: 4321-5/00 | F58: OBRAS E INSTALAÇÕES ELÉTRICAS | G58: EXCLUSIVAMENTE NO CLIENTE
A59: 5812-3/02 | B59: EDITOR(A) DE JORNAIS NÃO DIÁRIOS | C59: EXCLUSIVAMENTE NO CLIENTE / EXERCIDAS PELA INTERNET / COM IMPRESSÃO TERCEIRIZADA | E59: 4321-5/00 | F59: OBRAS INSTALAÇÕES ELÉTRICAS EM EDIFICAÇÕES | G59: EXCLUSIVAMENTE NO CLIENTE
A60: 5813-1/00 | B60: EDITOR(A) DE REVISTAS | C60: EXCLUSIVAMENTE NO CLIENTE / EXERCIDAS PELA INTERNET / COM IMPRESSÃO TERCEIRIZADA | E60: 4321-5/00 | F60: OBRAS PARA INSTALAÇÃO DE INTERFONE | G60: EXCLUSIVAMENTE NO CLIENTE
A61: 5819-1/00 | B61: EDITOR(A) DE LISTA DE DADOS E DE OUTRAS INFORMAÇÕES | C61: EXCLUSIVAMENTE NO CLIENTE / EXERCIDAS PELA INTERNET / COM IMPRESSÃO TERCEIRIZADA | E61: 4321-5/00 | F61: OBRAS PARA INSTALAÇÕES DE AUTOMAÇÃO BANCARIA | G61: EXCLUSIVAMENTE NO CLIENTE
A62: 5912-0/01 | B62: DUBLADOR(A) | E62: 4321-5/00 | F62: PREPARAÇÃO DE INSTALAÇÕES ELÉTRICAS PREDIAIS PARA POSSIBILITAR O USO DE APARELHOS E EQUIPAMENTOS DOMÉSTICOS | G62: EXCLUSIVAMENTE NO CLIENTE
A63: 5912-0/99 | B63: EDITOR(A) DE VÍDEO | E63: 4321-5/00 | F63: SERVIÇO DE ELETRICISTA RESIDENCIAL | G63: EXCLUSIVAMENTE NO CLIENTE
A64: 6190-6/99 | B64: INSTALADOR(A) DE REDE DE COMPUTADORES | E64: 4321-5/00 | F64: SERVIÇO DE INSTALAÇÃO ELÉTRICA RESIDENCIAL | G64: EXCLUSIVAMENTE NO CLIENTE
A65: 6399-2/00 | B65: APURADOR(A), COLETOR(A) E FORNECEDOR(A) DE RECORTES DE MATÉRIAS PUBLICADAS EM JORNAIS E REVISTAS | C65: EXCLUSIVAMENTE NO CLIENTE / EXERCIDAS PELA INTERNET | E65: 4322-3/01 | F65: INSTALAÇÃO DE ENCANAMENTOS | G65: EXCLUSIVAMENTE NO CLIENTE
A66: 7319-0/02 | B66: PANFLETEIRO(A) | E66: 4322-3/01 | F66: INSTALAÇÃO PLACAS COLETORAS PARA INSTALAÇÕES TÉRMICAS ALIMENTADAS POR ENERGIA SOLAR, QUANDO EXECUTADA POR UNIDADE ESPECIALIZADA | G66: EXCLUSIVAMENTE NO CLIENTE
A67: 7319-0/02 | B67: PROMOTOR(A) DE VENDAS | C67: EXCLUSIVAMENTE NO CLIENTE / SEM ESTOQUE DE PRODUTOS / SEM COMÉRCIO DE ALIMENTOS OU MEDICAMENTOS. | E67: 4322-3/01 | F67: INSTALAÇÕES HIDRÁULICAS, SANITÁRIAS E DE GÁS (CONSTRUÇÃO) | G67: EXCLUSIVAMENTE NO CLIENTE
A68: 7319-0/99 | B68: BIKE PROPAGANDISTA | E68: 4322-3/01 | F68: REPARAÇÃO OU MANUTENÇÃO, INSTALAÇÕES HIDRÁULICAS, SANITÁRIAS E DE GÁS | G68: EXCLUSIVAMENTE NO CLIENTE
A69: 7420-0/01 | B69: FOTÓGRAFO(A) | C69: SEM ESTÚDIO PRÓPRIO | E69: 4322-3/01 | F69: SERVIÇO DE ENCANAÇÃO RESIDENCIAL | G69: EXCLUSIVAMENTE NO CLIENTE
A70: 7420-0/02 | B70: FOTÓGRAFO(A) AÉREO | E70: 4322-3/01 | F70: SERVIÇO DE PREPARAÇÃO DE INSTALAÇÕES HIDRÁULICAS OU DE GÁS PREDIAIS PARA POSSIBILITAR O USO DE APARELHOS E EQUIPAMENTOS DOMÉSTICOS | G70: EXCLUSIVAMENTE NO CLIENTE
A71: 7420-0/02 | B71: FOTÓGRAFO(A) SUBMARINO | E71: 4322-3/01 | F71: SERVIÇOS HIDRÁULICOS | G71: EXCLUSIVAMENTE NO CLIENTE
A72: 7420-0/04 | B72: FILMADOR(A) | C72: SEM ESTÚDIO PRÓPRIO | E72: 4322-3/02 | F72: INSTALAÇÃO DE DUTOS PARA SISTEMAS DE AR CONDICIONADO | G72: EXCLUSIVAMENTE NO CLIENTE
A73: 7490-1/02 | B73: MERGULHADOR(A) (ESCAFANDRISTA) | E73: 4322-3/02 | F73: INSTALAÇÃO DE SISTEMAS CENTRAIS DE AQUECIMENTO CENTRAL EM EDIFÍCIOS RESIDENCIAIS E COMERCIAIS | G73: EXCLUSIVAMENTE NO CLIENTE
A74: 7911-2/00 | B74: AGENTE DE VIAGENS | C74: EXCLUSIVAMENTE NO CLIENTE / EXERCIDAS PELA INTERNET | E74: 4322-3/02 | F74: INSTALAÇÃO DE SISTEMAS CENTRAIS PARA CALEFAÇÃO | G74: EXCLUSIVAMENTE NO CLIENTE
A75: 7912-1/00 | B75: GUIA DE TURISMO | E75: 4322-3/02 | F75: INSTALAÇÃO DE SISTEMAS DE AR CONDICIONADO, DE VENTILAÇÃO E REFRIGERAÇÃO | G75: EXCLUSIVAMENTE NO CLIENTE
A76: 7990-2/00 | B76: PROMOTOR(A) DE TURISMO LOCAL | C76: EXCLUSIVAMENTE NO CLIENTE / EXERCIDAS PELA INTERNET | E76: 4322-3/02 | F76: INSTALAÇÃO DE SISTEMAS DE VENTILAÇÃO MECÂNICA CONTROLADA, INCLUSIVE EXAUSTORES | G76: EXCLUSIVAMENTE NO CLIENTE
A77: 8011-1/02 | B77: ADESTRADOR(A) DE CÃES DE GUARDA | C77: EXCLUSIVAMENTE NO CLIENTE | E77: 4322-3/02 | F77: MANUTENÇÃO DE AR CONDICIONADO CENTRAL | G77: EXCLUSIVAMENTE NO CLIENTE
A78: 8020-0/02 | B78: INSTALADOR(A) E REPARADOR DE COFRES, TRANCAS E TRAVAS DE SEGURANÇA | C78: EXCLUSIVAMENTE NO CLIENTE | E78: 4322-3/02 | F78: MONTAGEM DE SISTEMAS DE REFRIGERAÇÃO CENTRAL EM IMÓVEIS RESIDENCIAIS E COMERCIAIS | G78: EXCLUSIVAMENTE NO CLIENTE
A79: 8129-0/00 | B79: PISCINEIRO(A) | C79: EXCLUSIVAMENTE NO CLIENTE E SEM DEPÓSITO DE PRODUTOS QUÍMICOS | E79: 4322-3/02 | F79: REPARAÇÃO OU MANUTENÇÃO DE SISTEMA DE REFRIGERAÇÃO CENTRAL EM IMÓVEIS RESIDENCIAIS E COMERCIAIS | G79: EXCLUSIVAMENTE NO CLIENTE
A80: 8130-3/00 | B80: JARDINEIRO(A) | C80: SEM DEPÓSITO DE PRODUTOS QUÍMICOS | E80: 4322-3/02 | F80: REPARAÇÃO OU MANUTENÇÃO DE SISTEMA DE VENTILAÇÃO MECÂNICA CONTROLADA | G80: EXCLUSIVAMENTE NO CLIENTE
A81: 8219-9/99 | B81: DIGITADOR(A) | C81: EXCLUSIVAMENTE NO CLIENTE / EXERCIDAS PELA INTERNET | E81: 4322-3/03 | F81: INSTALAÇÃO DE ALARME ANTI-FOGO | G81: EXCLUSIVAMENTE NO CLIENTE
A82: 8230-0/01 | B82: PROMOTOR(A) DE EVENTOS | C82: EXCLUSIVAMENTE NO CLIENTE | E82: 4322-3/03 | F82: INSTALAÇÃO DE EQUIPAMENTOS EXTINTORES DE INCÊNDIO | G82: EXCLUSIVAMENTE NO CLIENTE
A83: 8291-1/00 | B83: COBRADOR(A) DE DÍVIDAS | C83: EXCLUSIVAMENTE NO CLIENTE | E83: 4322-3/03 | F83: INSTALAÇÃO DE SISTEMA DE DETECÇÃO DE INCÊNDIO | G83: EXCLUSIVAMENTE NO CLIENTE
A84: 8592-9/02 | B84: INSTRUTOR(A) DE ARTES CÊNICAS | C84: EXCLUSIVAMENTE NO CLIENTE / EXERCIDAS PELA INTERNET | E84: 4322-3/03 | F84: INSTALAÇÃO DE SISTEMAS DE PREVENÇÃO CONTRA INCÊNDIO | G84: EXCLUSIVAMENTE NO CLIENTE
A85: 8592-9/03 | B85: INSTRUTOR(A) DE MÚSICA | C85: EXCLUSIVAMENTE NO CLIENTE / EXERCIDAS PELA INTERNET | E85: 4322-3/03 | F85: INSTALAÇÃO DE SPRINKLERS AUTOMÁTICOS CONTRA FOGO | G85: EXCLUSIVAMENTE NO CLIENTE
A86: 8592-9/99 | B86: INSTRUTOR(A) DE ARTE E CULTURA EM GERAL | C86: EXCLUSIVAMENTE NO CLIENTE / EXERCIDAS PELA INTERNET | E86: 4322-3/03 | F86: INSTALAÇÕES DE SISTEMAS DE PREVENÇÃO CONTRA INCÊNDIO (CONSTRUÇÃO) | G86: EXCLUSIVAMENTE NO CLIENTE
A87: 8593-7/00 | B87: INSTRUTOR(A) DE IDIOMAS | C87: EXCLUSIVAMENTE NO CLIENTE / EXERCIDAS PELA INTERNET | E87: 4322-3/03 | F87: MANUTENÇÃO DE SISTEMAS DE ALARME CONTRA INCÊNDIO | G87: EXCLUSIVAMENTE NO CLIENTE
... A111: 9700-5/00 | B111: DIARISTA | C111: EXCLUSIVAMENTE NO CLIENTE E SEM DEPÓSITO DE PRODUTOS QUÍMICOS | E111: 4330-4/02 | F111: COLOCAÇÃO DE ARMÁRIOS DE COZINHAS PLANEJADAS QUANDO EXECUTADA POR UNIDADE ESPECIALIZADA | G111: EXCLUSIVAMENTE NO CLIENTE
E112: 4330-4/02 | F112: COLOCAÇÃO DE ARMÁRIOS EMBUTIDOS QUANDO EXECUTADA POR UNIDADE ESPECIALIZADA | G112: EXCLUSIVAMENTE NO CLIENTE
E113: 4330-4/02 | F113: FIXAÇÃO DE CABECEIRAS E PEITORIS (OU SOLEIRAS) | G113: EXCLUSIVAMENTE NO CLIENTE
E114: 4330-4/02 | F114: FIXAÇÃO DE ESQUADRIAS (CHUMBAMENTO) NA CONSTRUÇÃO | G114: EXCLUSIVAMENTE NO CLIENTE
E115: 4330-4/02 | F115: INSTALAÇÃO DE (QUANDO EXECUTADA POR UNIDADE ESPECIALIZADA) COZINHAS EQUIPADAS | G115: EXCLUSIVAMENTE NO CLIENTE
E116: 4330-4/02 | F116: INSTALAÇÃO DE DOBRADIÇAS, FECHADURAS, TRANCAS E OUTRAS FERRAGENS EM ESQUADRIAS QUANDO EXECUTADA POR UNIDADE ESPECIALIZADA | G116: EXCLUSIVAMENTE NO CLIENTE
E117: 4330-4/02 | F117: INSTALAÇÃO DE ESCADAS (QUANDO EXECUTADA POR UNIDADE ESPECIALIZADA) | G117: EXCLUSIVAMENTE NO CLIENTE
E118: 4330-4/02 | F118: INSTALAÇÃO DE ESQUADRIAS DE METAL, MADEIRA, PVC OU QUALQUER OUTRO MATERIAL, QUANDO EXECUTADA POR UNIDADE ESPECIALIZADA | G118: EXCLUSIVAMENTE NO CLIENTE
E119: 4330-4/02 | F119: INSTALAÇÃO DE ESTANDES (STANDS) PARA FEIRAS E EVENTOS | G119: EXCLUSIVAMENTE NO CLIENTE
E120: 4330-4/02 | F120: MANUTENÇÃO DE CARPINTARIA, TRABALHOS DE CARPINTARIA | G120: EXCLUSIVAMENTE NO CLIENTE
E121: 4330-4/03 | F121: ACABAMENTOS EM GESSO | G121: EXCLUSIVAMENTE NO CLIENTE / SEM DEPÓSITO DE MATERIAL
E122: 4330-4/03 | F122: APLICAÇÃO DE ESTUQUE VENEZIANO EM PAREDES | G122: EXCLUSIVAMENTE NO CLIENTE / SEM DEPÓSITO DE MATERIAL
E123: 4330-4/03 | F123: APLICAÇÃO DE FORRO DE PLACAS DE GESSO. | G123: EXCLUSIVAMENTE NO CLIENTE / SEM DEPÓSITO DE MATERIAL
... E455: 4929-9/02 | F455: TRANSPORTE RODOVIÁRIO COLETIVO DE PASSAGEIROS, SOB REGIME DE FRETAMENTO, INTERMUNICIPAL, INTERESTADUAL E INTERNACIONAL. | G455: NÃO UTILIZAR VIA PÚBLICA COMO LOCAL DE GUARDA DO VEÍCULO QUANDO O MESMO NÃO ESTIVER EM SERVIÇO.
E456: 4929-9/03 | F456: ORGANIZAÇÃO DE EXCURSÕES EM VEÍCULOS RODOVIÁRIOS PRÓPRIOS, MUNICIPAL
E457: 4929-9/03 | F457: ORGANIZAÇÃO DE EXCURSÕES EM VEÍCULOS RODOVIÁRIOS PRÓPRIOS, MUNICIPAL | G457: NÃO UTILIZAR VIA PÚBLICA COMO LOCAL DE GUARDA DO VEÍCULO QUANDO O MESMO NÃO ESTIVER EM SERVIÇO.
E458: 4929-9/04 | F458: ORGANIZAÇÃO DE EXCURSÕES EM VEÍCULOS RODOVIÁRIOS PRÓPRIOS, INTERMUNICIPAL, INTERESTADUAL E INTERNACIONAL | G458: NÃO UTILIZAR VIA PÚBLICA COMO LOCAL DE GUARDA DO VEÍCULO QUANDO O MESMO NÃO ESTIVER EM SERVIÇO.
E459: 5212-5/00 | F459: SERVIÇOS DE CARGA E DESCARGA | G459: EXCLUSIVAMENTE NO CLIENTE
E460: 5212-5/00 | F460: SERVIÇOS DE CARREGAMENTO E DESCARREGAMENTO DE BAGAGENS | G460: EXCLUSIVAMENTE NO CLIENTE
E461: 5212-5/00 | F461: SERVIÇOS DE MANUSEIO DE BAGAGENS | G461: EXCLUSIVAMENTE NO CLIENTE
E462: 5212-5/00 | F462: SERVIÇOS DE PATIAMENTO DE CARROS | G462: EXCLUSIVAMENTE NO CLIENTE
E463: 5250-8/01 | F463: ASSESSORIA EM IMPORTAÇÃO E EXPORTAÇÃO DE CARGAS | G463: EXCLUSIVAMENTE NO CLIENTE / EXERCIDAS PELA INTERNET
E464: 5250-8/01 | F464: SERVIÇOS DE ASSESSORIA ADUANEIRA | G464: EXCLUSIVAMENTE NO CLIENTE / EXERCIDAS PELA INTERNET
E465: 5250-8/01 | F465: SERVIÇOS DE COMISSARIA DE DESPACHOS | G465: EXCLUSIVAMENTE NO CLIENTE / EXERCIDAS PELA INTERNET
E466: 5250-8/01 | F466: SERVIÇOS DE DESEMBARAÇO ADUANEIRO | G466: EXCLUSIVAMENTE NO CLIENTE / EXERCIDAS PELA INTERNET
E467: 5250-8/01 | F467: SERVIÇOS DE REGULARIZAÇÃO DE DOCUMENTOS SOBRE ENTRADA E SAÍDA DE MERCADORIAS | G467: EXCLUSIVAMENTE NO CLIENTE / EXERCIDAS PELA INTERNET
E468: 5250-8/01 | F468: SERVIÇOS DE REGULARIZAÇÃO DE IMPOSTOS SOBRE MERCADORIAS | G468: EXCLUSIVAMENTE NO CLIENTE / EXERCIDAS PELA INTERNET
... E470: 5250-8/01 | F470: SERVIÇOS DE TRÂMITES PARA DESEMBARAÇO ALFANDEGÁRIO E ADUANEIRO | G470: EXCLUSIVAMENTE NO CLIENTE / EXERCIDAS PELA INTERNET
E471: 5320-2/01 | F471: SERVIÇOS DE COLETA, DISTRIBUIÇÃO E ENTREGA DE CORRESPONDÊNCIA E VOLUMES
...

Sheet Atividades 2
A1: OUTROS
A2: CNAE | B2: DESCRIÇÃO SUBCLASSE CNAE | C2: Restrição que deve constar no objeto social, para a liberação do Alvará de Licença de Atividade
A3: 3321-0/00 | B3: INSTALAÇÃO E MONTAGEM DE APARELHOS E EQUIPAMENTOS DE IRRADIAÇÃO ELETROMÉDICOS E ELETROTERAPÊUTICOS | C3: EXCLUSIVAMENTE NO CLIENTE
A4: 3321-0/00 | B4: INSTALAÇÃO E MONTAGEM DE EQUIPAMENTOS E INSTRU- MENTOS DE MEDIDA, TESTE E CONTROLE | C4: EXCLUSIVAMENTE NO CLIENTE
A5: 3321-0/00 | B5: INSTALAÇÃO E MONTAGEM DE GERADORES, TRANSFORMADO- RES, MOTORES E OUTROS EQUIPAMENTOS ELÉTRICOS | C5: EXCLUSIVAMENTE NO CLIENTE
A6: 3321-0/00 | B6: INSTALAÇÃO E MONTAGEM DE MÁQUINAS E EQUIPAMENTOS PARA INDUSTRIA DO PLÁSTICO | C6: EXCLUSIVAMENTE NO CLIENTE
A7: 3321-0/00 | B7: INSTALAÇÃO E MONTAGEM DE MÁQUINAS E EQUIPAMENTOS PARA INDUSTRIA TÊXTIL, DO VESTUÁRIO, COURO E CALÇADOS | C7: EXCLUSIVAMENTE NO CLIENTE
A8: 3321-0/00 | B8: INSTALAÇÃO E MONTAGEM DE MÁQUINAS E EQUIPAMENTOS PARA TERRAPLENAGEM, PAVIMENTAÇÃO E CONSTRUÇÃO | C8: EXCLUSIVAMENTE NO CLIENTE
A9: 3321-0/00 | B9: INSTALAÇÃO E MONTAGEM DE MÁQUINAS E EQUIPAMENTOS PARA USO AGRÍCOLA | C9: EXCLUSIVAMENTE NO CLIENTE
A10: 3321-0/00 | B10: INSTALAÇÃO E MONTAGEM DE MÁQUINAS E EQUIPAMENTOS PARA USO GERAL | C10: EXCLUSIVAMENTE NO CLIENTE
A11: 3321-0/00 | B11: INSTALAÇÃO E MONTAGEM DE MÁQUINAS E EQUIPAMENTOS PARA USO NA EXTRAÇÃO MINERAL, | C11: EXCLUSIVAMENTE NO CLIENTE
A12: 3321-0/00 | B12: INSTALAÇÃO E MONTAGEM DE MÁQUINAS E EQUIPAMENTOS PARA USOS INDUSTRIAIS ESPECÍFICO | C12: EXCLUSIVAMENTE NO CLIENTE
A13: 3321-0/00 | B13: INSTALAÇÃO E MONTAGEM DE MÁQUINAS-FERRAMENTA | C13: EXCLUSIVAMENTE NO CLIENTE
... A23: 3329-5/01 | B23: MONTAGEM DE MOVEIS DE QUALQUER MATERIAL PARA CON- SUMIDOR FINAL, NÃO ASSOCIADA AO COMÉRCIO, QUANDO EXECUTADA POR UNIDADE ESPECIALIZADA | C23: EXCLUSIVAMENTE NO CLIENTE
A24: 4110-7/00 | B24: INCORPORAÇÃO DE IMÓVEIS POR CONTA PRÓPRIA
A25: 4110-7/00 | B25: INCORPORAÇÃO DE IMÓVEIS PRÓPRIOS
A26: 4321-5/00 | B26: CONSTRUÇÃO E MANUTENÇÃO DE INSTALAÇÕES PARA CEN- TRO DE PROCESSAMENTO DE DADOS | C26: EXCLUSIVAMENTE NO CLIENTE
A27: 4321-5/00 | B27: CPD, CONSTRUÇÃO E MANUTENÇÃO DE INSTALAÇÕES | C27: EXCLUSIVAMENTE NO CLIENTE
A28: 4321-5/00 | B28: INSTALAÇÃO DE ALARME CONTRA ROUBO EM EDIFICAÇÕES | C28: EXCLUSIVAMENTE NO CLIENTE
A29: 4321-5/00 | B29: INSTALAÇÃO DE ANTENAS COLETIVAS E PARABÓLICAS | C29: EXCLUSIVAMENTE NO CLIENTE
A30: 4321-5/00 | B30: INSTALAÇÃO DE ANTENAS DE TELEVISÃO | C30: EXCLUSIVAMENTE NO CLIENTE
A31: 4321-5/00 | B31: INSTALAÇÃO DE CABEAÇÃO LÓGICA | C31: EXCLUSIVAMENTE NO CLIENTE
A32: 4321-5/00 | B32: INSTALAÇÃO DE CABOS PARA INSTALAÇÕES DE COMUNICAÇÃO E INFORMÁTICA EM EDIFICAÇÕES | C32: EXCLUSIVAMENTE NO CLIENTE
A33: 4321-5/00 | B33: INSTALAÇÃO DE CABOS PARA INSTALAÇÕES TELEFÔNICAS EM EDIFICAÇÕES | C33: EXCLUSIVAMENTE NO CLIENTE
A34: 4321-5/00 | B34: INSTALAÇÃO DE CABOS PARA TELEVISÃO EM EDIFICAÇÕES | C34: EXCLUSIVAMENTE NO CLIENTE
A35: 4321-5/00 | B35: INSTALAÇÃO DE CAIXAS DE ENTRADA DE ENERGIA EM EDIFICA- ÇÕES | C35: EXCLUSIVAMENTE NO CLIENTE
A36: 4321-5/00 | B36: INSTALAÇÃO DE EQUIPAMENTOS DE INTERCOMUNICAÇÃO EM EDIFICAÇÕES | C36: EXCLUSIVAMENTE NO CLIENTE
A37: 4321-5/00 | B37: INSTALAÇÃO DE PADRÃO DE ENERGIA (CAIXAS, QUADROS, PAI- NÉIS OU CUBÍCULOS) | C37: EXCLUSIVAMENTE NO CLIENTE
... A459: 4619-2/00 | B459: REPRESENTAÇÃO COMERCIAL E AGENTE DO COMÉRCIO DE PRODUTOS DIVERSOS | C459: SEM DEPÓSITO DE MERCADORIAS
A460: 4929-9/03 | B460: ORGANIZAÇÃO DE EXCURSÕES EM VEÍCULOS RODOVIÁRIOS PRÓPRIOS, MUNICIPAL
A461: 5212-5/00 | B461: SERVIÇOS DE CARGA E DESCARGA | C461: EXCLUSIVAMENTE NO CLIENTE
A462: 5212-5/00 | B462: SERVIÇOS DE CARREGAMENTO E DESCARREGAMENTO DE BA- GAGENS | C462: EXCLUSIVAMENTE NO CLIENTE
A463: 5212-5/00 | B463: SERVIÇOS DE MANUSEIO DE BAGAGENS | C463: EXCLUSIVAMENTE NO CLIENTE
A464: 5212-5/00 | B464: SERVIÇOS DE PATIAMENTO DE CARROS | C464: EXCLUSIVAMENTE NO CLIENTE
A465: 5250-8/01 | B465: ASSESSORIA EM IMPORTAÇÃO E EXPORTAÇÃO DE CARGAS | C465: EXCLUSIVAMENTE NO CLIENTE / EXERCIDAS PELA INTERNET
A466: 5250-8/01 | B466: SERVIÇOS DE ASSESSORIA ADUANEIRA | C466: EXCLUSIVAMENTE NO CLIENTE / EXERCIDAS PELA INTERNET
A467: 5250-8/01 | B467: SERVIÇOS DE COMISSARIA DE DESPACHOS | C467: EXCLUSIVAMENTE NO CLIENTE / EXERCIDAS PELA INTERNET
A468: 5250-8/01 | B468: SERVIÇOS DE DESEMBARAÇO ADUANEIRO | C468: EXCLUSIVAMENTE NO CLIENTE / EXERCIDAS PELA INTERNET
A469: 5250-8/01 | B469: SERVIÇOS DE REGULARIZAÇÃO DE DOCUMENTOS SOBRE EN- TRADA E SAÍDA DE MERCADORIAS | C469: EXCLUSIVAMENTE NO CLIENTE / EXERCIDAS PELA INTERNET
A470: 5250-8/01 | B470: SERVIÇOS DE REGULARIZAÇÃO DE IMPOSTOS SOBRE MERCA- DORIAS | C470: EXCLUSIVAMENTE NO CLIENTE / EXERCIDAS PELA INTERNET
A471: 5250-8/01 | B471: SERVIÇOS DE TRÂMITES DO COMÉRCIO EXTERIOR REALIZADO POR EMPRESAS DE COMISSARIA DE DESPACHO | C471: EXCLUSIVAMENTE NO CLIENTE / EXERCIDAS PELA INTERNET
A472: 5250-8/01 | B472: SERVIÇOS DE TRÂMITES PARA DESEMBARAÇO ALFANDEGÁRIO E ADUANEIRO | C472: EXCLUSIVAMENTE NO CLIENTE / EXERCIDAS PELA INTERNET
A473: 5320-2/01 | B473: SERVIÇOS DE COLETA, DISTRIBUIÇÃO E ENTREGA DE CORRES- PONDÊNCIA E VOLUMES
A474: 5320-2/01 | B474: SERVIÇOS DE COLETA, TRANSPORTE E ENTREGA DE DOCUMEN- TOS POR TERCEIROS
A475: 5320-2/01 | B475: SERVIÇOS DE COURRIER
A476: 5320-2/01 | B476: SERVIÇOS DE ENTREGA DE CARTAS, CONVITES E SIMILARES POR TERCEIROS
A477: 5320-2/01 | B477: SERVIÇOS DE ENTREGA EXPRESSA DE DOCUMENTOS POR TER- CEIROS
A478: 5320-2/01 | B478: SERVIÇOS DE ENTREGA RÁPIDA DE DOCUMENTOS E MALOTES, POR TERCEIROS
A479: 5320-2/02 | B479: COLETA DE ENCOMENDAS
A480: 5320-2/02 | B480: DISTRIBUIÇÃO DE JORNAIS EM DOMICÍLIOS
A481: 5320-2/02 | B481: ENTREGA DE JORNAIS E REVISTAS EM DOMICÍLIO SOB CONTRA- TO | C481: Exclusivo a entrega, sem triagem ou elaboração de rota. Sem con-
A482: 5320-2/02 | B482: ENTREGA DE REFEIÇÕES, ALIMENTOS PARA RESTAURANTES | C482: O VEÍCULO OU DISPOSITIVO DE ACONDICIONAMENTO SERÁ EX- CLUSIVO PARA A ATIVIDADE DE ALIMENTOS.
A483: 5811-5/00 | B483: EDIÇÃO DE APOSTILAS | C483: COM IMPRESSÃO TERCEIRIZADA
A484: 5811-5/00 | B484: EDIÇÃO DE ATLAS | C484: COM IMPRESSÃO TERCEIRIZADA
A485: 5811-5/00 | B485: EDIÇÃO DE ENCICLOPÉDIAS | C485: COM IMPRESSÃO TERCEIRIZADA
A486: 5811-5/00 | B486: EDIÇÃO DE LIVROS ELETRÔNICOS | C486: COM IMPRESSÃO TERCEIRIZADA
A487: 5811-5/00 | B487: EDIÇÃO DE LIVROS EM GERAL | C487: COM IMPRESSÃO TERCEIRIZADA
A488: 5811-5/00 | B488: EDIÇÃO DE LIVROS INFANTIS | C488: COM IMPRESSÃO TERCEIRIZADA
A489: 5811-5/00 | B489: EDIÇÃO DE LIVROS NA INTERNET | C489: COM IMPRESSÃO TERCEIRIZADA
A490: 5811-5/00 | B490: EDIÇÃO DE LIVROS TÉCNICOS | C490: COM IMPRESSÃO TERCEIRIZADA
A491: 5811-5/00 | B491: EDIÇÃO DE MAPAS | C491: COM IMPRESSÃO TERCEIRIZADA
A492: 5811-5/00 | B492: EDIÇÃO DE OBRAS LITERÁRIAS | C492: COM IMPRESSÃO TERCEIRIZADA
A493: 5811-5/00 | B493: GESTÃO DE DIREITOS AUTORAIS DE OBRAS LITERÁRIAS
A494: 5811-5/00 | B494: OBRAS LITERÁRIAS AQUISIÇÃO DE DIREITOS AUTORAIS
A495: 5812-3/01 | B495: EDIÇÃO DE JORNAIS ELETRÔNICOS DIÁRIOS | C495: COM IMPRESSÃO TERCEIRIZADA
A496: 5812-3/01 | B496: EDIÇÃO DE JORNAIS IMPRESSOS DIÁRIOS | C496: COM IMPRESSÃO TERCEIRIZADA
A497: 5812-3/01 | B497: EDIÇÃO DE JORNAIS NA INTERNET DIÁRIOS | C497: COM IMPRESSÃO TERCEIRIZADA
A498: 5812-3/01 | B498: EDIÇÃO DE JORNAIS PUBLICITÁRIOS DIÁRIOS | C498: COM IMPRESSÃO TERCEIRIZADA
A499: 5812-3/02 | B499: EDIÇÃO DE JORNAIS ELETRÔNICOS NÃO DIÁRIOS | C499: COM IMPRESSÃO TERCEIRIZADA
A500: 5812-3/02 | B500: EDIÇÃO DE JORNAIS IMPRESSOS NÃO DIÁRIOS | C500: COM IMPRESSÃO TERCEIRIZADA
A501: 5812-3/02 | B501: EDIÇÃO DE JORNAIS NA INTERNET NÃO DIÁRIOS | C501: COM IMPRESSÃO TERCEIRIZADA
A502: 5812-3/02 | B502: EDIÇÃO DE JORNAIS PUBLICITÁRIOS NÃO DIÁRIOS | C502: COM IMPRESSÃO TERCEIRIZADA
A503: 5813-1/00 | B503: EDIÇÃO DE PUBLICAÇÕES PERIÓDICAS | C503: COM IMPRESSÃO TERCEIRIZADA
A504: 5813-1/00 | B504: EDIÇÃO DE REVISTAS DE CONTEÚDO TÉCNICO OU GERAL | C504: COM IMPRESSÃO TERCEIRIZADA
A505: 5813-1/00 | B505: EDIÇÃO DE REVISTAS DE PROGRAMAÇÃO DE TELEVISÃO | C505: COM IMPRESSÃO TERCEIRIZADA
A506: 5813-1/00 | B506: EDIÇÃO DE REVISTAS ELETRÔNICAS | C506: COM IMPRESSÃO TERCEIRIZADA
... A537: 5920-1/00 | B537: GESTÃO DE DIREITOS AUTORAIS DE OBRAS MUSICAIS | C537: EXCLUSIVAMENTE NO CLIENTE
A538: 6190-6/99 | B538: INSTALAÇÃO E MANUTENÇÃO DAS CONEXÕES DE TERMINAIS DE REDE DE TELECOMUNICAÇÃO EM PRÉDIOS
A539: 6190-6/99 | B539: SERVIÇOS DE CONEXÃO E DE REDES DE TELECOMUNICAÇÕES EM PRÉDIOS
A540: 6190-6/99 | B540: SERVIÇOS DE INSTALAÇÃO E MANUTENÇÃO DE LINHAS DE TE- LEFONES PARTICULARES
A541: 6190-6/99 | B541: SERVIÇOS DE INSTALAÇÃO E MANUTENÇÃO DE LINHAS DE TE- LEFONES PÚBLICOS
A542: 6190-6/99 | B542: SERVIÇOS DE INSTALAÇÃO E MANUTENÇÃO DE SUPORTES PARA CIRCUITOS DE DADOS
A543: 6201-5/01 | B543: CRIAÇÃO, CONFIGURAÇÃO DE SOFTWARE DE BANCO DE DA- DOS SOB ENCOMENDA | C543: EXCLUSIVAMENTE NO CLIENTE / EXERCIDAS PELA INTERNET
A544: 6201-5/01 | B544: DESENVOLVIMENTO DE APLICATIVO INFORMÁTICO SOB ENCO- MENDA | C544: EXCLUSIVAMENTE NO CLIENTE / EXERCIDAS PELA INTERNET
A545: 6201-5/01 | B545: DESENVOLVIMENTO DE BANCO DE DADOS SOB ENCOMENDA | C545: EXCLUSIVAMENTE NO CLIENTE / EXERCIDAS PELA INTERNET
A546: 6201-5/01 | B546: DESENVOLVIMENTO DE PROJETOS E MODELAGEM DE BANCO DE DADOS SOB ENCOMENDA | C546: EXCLUSIVAMENTE NO CLIENTE / EXERCIDAS PELA INTERNET
A547: 6201-5/01 | B547: DESENVOLVIMENTO, PRODUÇÃO, DOCUMENTAÇÃO DE PRO- GRAMAS DE INFORMÁTICA SOB ENCOMENDA | C547: EXCLUSIVAMENTE NO CLIENTE / EXERCIDAS PELA INTERNET
A548: 6201-5/01 | B548: ELABORAÇÃO DE PROGRAMAS DE BANCO DE DADOS SOB EN- COMENDA | C548: EXCLUSIVAMENTE NO CLIENTE / EXERCIDAS PELA INTERNET
A549: 6201-5/01 | B549: ELABORAÇÃO DE PROGRAMAS DE COMPUTADOR SOB ENCO- MENDA | C549: EXCLUSIVAMENTE NO CLIENTE / EXERCIDAS PELA INTERNET
A550: 6201-5/01 | B550: SERVIÇOS DE EDIÇÃO DE SOFTWARE SOB ENCOMENDA | C550: EXCLUSIVAMENTE NO CLIENTE / EXERCIDAS PELA INTERNET
A551: 6201-5/01 | B551: SERVIÇOS DE EDIÇÃO ON LINE DE BANCO DE DADOS | C551: EXCLUSIVAMENTE NO CLIENTE / EXERCIDAS PELA INTERNET
A552: 6201-5/02 | B552: DESENVOLVIMENTO CRIAÇÃO DE PÁGINAS NA INTERNET | C552: EXCLUSIVAMENTE NO CLIENTE / EXERCIDAS PELA INTERNET
A553: 6201-5/02 | B553: SERVIÇOS DE EDIÇÃO DE SITE | C553: EXCLUSIVAMENTE NO CLIENTE / EXERCIDAS PELA INTERNET
A554: 6201-5/02 | B554: SERVIÇOS DE PORTAIS NA INTERNET CONFECÇÃO | C554: EXCLUSIVAMENTE NO CLIENTE / EXERCIDAS PELA INTERNET
... A575: 6204-0/00 | B575: ASSESSORIA PARA COMPRA E INSTALAÇÃO DE PERIFÉRICOS | C575: EXCLUSIVAMENTE NO CLIENTE /
C577: EXERCIDAS PELA INTERNET
A578: 6204-0/00 | B578: ASSESSORIA, CONSULTORIA EM INFORMÁTICA | C578: EXCLUSIVAMENTE NO CLIENTE / EXERCIDAS PELA INTERNET
A579: 6204-0/00 | B579: ASSESSORIA, CONSULTORIA EM SISTEMAS DE INFORMÁTICA | C579: EXCLUSIVAMENTE NO CLIENTE / EXERCIDAS PELA INTERNET
A580: 6204-0/00 | B580: CONSULTORIA EM ANÁLISE DE SISTEMAS | C580: EXCLUSIVAMENTE NO CLIENTE / EXERCIDAS PELA INTERNET
A581: 6204-0/00 | B581: CONSULTORIA EM HARDWARE E SOFTWARE | C581: EXCLUSIVAMENTE NO CLIENTE / EXERCIDAS PELA INTERNET
...

Sheet Página2
